Workbook

Sheet 0 - Home
B3: Overview
B4: This document aims to provide an outline of some key information captured regarding the project/application
B6: Project form
B7: Questionnaire to describe project contacts and stakeholdersand also to assess security and risk level of the project through defined metrics & indicators Please contact : GroupSecurity@sephora.fr if you have any question
B10: Disclaimer
B11: Please keep in mind that the following requierments should be taken into account before completing the document
B12: Identify what type data (see Confidentiality scale) is impacted, modified or created by the project | C12: Identify the personal data that will be collected, stored, transferred | D12: Involve your Local Data Privacy Contact if your project includes personal data | E12: Do not duplicate data in this project that already exists in other projects. | F12: Before any data is shared, work with Privacy/Legal team to put the relevant contract or, privacy clause or NDA are in place
B14: Tab | C14: Objectives
B15: 0 - Home | C15: The Guidelines sheet aims to present the different tabs of this sheet.
B16: 1 - General description | C16: The General description tab aims to present the general descriptive information about the IT project regardless of security of privacy aspects. More specificly, the sheet is devided in two sections : 1. General description The IT Project Manager has to provide descriptive information, such as the Project Title, the Business Domain, the objectives and the scope of the project etc. The Project Manager has to give information about the global architecture, the role of 3rd parties, the technological context (mobility, IoT, industrial systems...) and some use cases (number and type of users) in order to better assess the exposure of the project. 2. Main components The Project Manager has to list the different components (applications, systems and interfaces) that are part of the project. 3. Sub-contractors : The Project Manager has to list the different sub-contractors of the project by giving their name, explaining their role and listing the different documents integrated for assessment and agreement. 4. General questions The IT Project Manager must indicate all the use-cases corresponding the service provided to Sephora by writing "Yes" (instead of "No") on the appropriated lines.
B17: 2 - Qualification | C17: The Qualification tab aims to evaluate the security and privacy requirements and provides a first insight about exposure of this project. This includes global data mapping, evaluating the requirements of security and providing indicators about exposure. This sheet is divided in two different sections : 1. Data mapping : in this section, the Project Manager has to list the categories of data, and to specify if the project handles personal and/or strategic data. This enables to assess a sensitivity level especially for privacy. 2. Security requirements : The Project Manager has to define the requirements according to 6 criteria : Confidentiality, Integrity, Availability, Traceability, Privacy and Compliance from an business impact point of view.
B18: 3 - 3rd Security Party Policy | C18: The Applicability column (H) is automatically updated depending on the use-cases declared in "1 - General description" tab. It indicated the requirements to which an answer is necessary. For each requirement/line declared as applicable, you must fulfill the compliance level (column I): Not Compliant / Partial / Full. If a requirement is answered as non compliant or partially compliant: you must provide details about the reasons of the non compliance, about potential measures already implemented, or roadmap elements if projects are planned which may lead to a compliance. Those details can be provided in the J and K column. Warning: apart from columns I, J, K and L no other columns should be manually modified. This document becomes an appendix to the contract between the customer and the supplier.
B19: 4 - 3rd Party Assessment | C19: The 3rd Party Assessment tab aims to evaluate the organizational security of the partner as well as the technical security of the proposed solution. In this assessment, the partner is expected to support its answers with documents/policies/processes/certifications/audit results that will prove the security level of the solution and its organization.
B20: 5 - Risk Assessment | C20: The Risk assessment tab is the tool with which the IT Project Manager will make risk analysis and the DPIA if decided in the Data Privacy Focus (option) tab. One risks are assessed, countermeasures must be selected to reduce/avoid/transfer the risks (reduce impact or likelihood). It's an iterative approach. Measures must be added until residual risk is acceptable. This sheet is divided into two main parts : 1. Top risks (cyber and privacy) The IP Project Manager gives a list of top risks and associated threat scenarios, description and scoring of the potential impacts from a coporate point of view and from the subjects point of view (for PIA), assess likelihood and calculates risk score. 2. Security measures The Project Manager has to list all the countermeasures : those already implemented (transversal) and the specific measures to reduce the risks identified above.

Sheet 1 - General description
B2: GENERAL DESCRIPTION
B3: Project Title | C3: Livstick
B4: Objectives
B5: Main Functions
B6: Business Domain | C6: Digital | E6: Will the solution be used by mobile devices (smartphones, tablets…) ? | F6: No | H6: Business Sponsor | I6: Jérome OUGIER LABERGERE
B7: Department | C7: Figital | H7: Business Application Owner | I7: Margaux NOBRE
B8: Scope | C8: Local market | H8: IT Project Manager (Build & change)
B9: Operational points | C9: HQ | E9: Does the solution involve industrial systems ? | F9: No | H9: IT Application Manager (Run)
B10: Hosting | C10: External - Cloud SaaS | H10: Business Security Referent | I10: imane MILOUD
B11: Exposure | C11: Cloud / SaaS | H11: Security key contact | I11: Paul BLAISE
B12: Frequency | C12: Permanent | E12: Does the solution involve connected objects (IoT) ? | F12: No | H12: Local DPC (Data Privacy Contact)
B13: Integration with internal information system | C13: Yes | H13: Is the solution a POC ?
B14: API | C14: Yes | E14: Does the solution involve the usage or development of AI ? | F14: Yes | H14: Production start date
B16: =IF(C8="Global",4,IF(C8="Region",3,IF(C8="Local market",2,0))) -> 2 | C16: =IF(C10="Sephora - On premises",1,IF(C10="Sephora - Cloud",2,IF(C10="External - Cloud SaaS",3,IF(C10="External - Cloud IaaS/PaaS",4,IF(C10="External - Private SaaS",5,IF(C10="External - Private IaaS/PaaS",6,0)))))) -> 3 | D16: =IF(C11="Internet",4,IF(C11="Cloud / SaaS",3,IF(C11="Standalone",3,IF(C11="Intranet - On premises",2,0)))) -> 3
B17: Main components : applications, systems and interfaces
B18: Component name | C18: Type | D18: Editor | E18: Hosting | F18: Comment
B25: Sub-contractors
B26: Sub-contractor name | C26: Role | D26: Security & Data protection clauses | E26: 3rd party security policy | F26: Security Assurance Plan | G26: Reversibility Plan | H26: Hosting | I26: Comment
B33: GENERAL QUESTIONS TO BE FILLED BY ALL COMPANIES
B34: General questions about the service / Questions générales sur la prestation
B35: General questions / Questions générales | E35: To be filled by the Company / A remplir par la Société | G35: Client comments / Commentaires du Client
B36: Consultancy/audit services, survey in any business or support activity (ex: marketing, medias, sales, finance, HR, IT, logistics, general services, architecture, decoration,…) which need exchange means and temporary storage (data, documents) to ensure communication with the Customer? / Des prestations de type études/conseils/audits/enquêtes dans tout domaine d'activité métier ou support ? (ex: marketing, médias, vente , finance, RH, IT, logistique, services généraux, architecture, décoration…) nécessitant notamment des moyens d’échange et de stockage temporaires d'information (documents, données) pour assurer la communication avec le Client. | E36: No
B37: Provider's connection to the client's network for maintenance, support and/or operation on non-IT technical components? Examples: on-site maintenance of electrical installation, air conditionning, shop lighting, CCTV, intrusion detection, remote maintenance of electrical installation, physical access control system management / Des connexions du prestataire à des fins de maintenance, support et/ou d'exploitation, sur des composants techniques non IT, mais raccordés au réseau du client ? Exemples : maintenance sur site installation électrique, climatisation, éclairage boutique, vidéosurveillance, détection intrusion, maintenance à distance installation électrique, gestion système de contrôle d'accès physique | E37: No
B38: Operational/Support/Maintenance intervention on IT ressources of the Customer? Examples: administration of systems, networks or databaseslocal user support, TMA, managed services / Des interventions d'exploitation, de support ou de maintenance sur le Système d'Information du client ? Exemples : administration de systèmes, réseaux ou bases de données sur site, support de proximité aux utilisateurs, TMA, Infogérance | E38: No
B39: Is the service provided a call center activity? / Est-ce qu'un center d'appel est utilisé dans le cadre de la prestation ? | E39: No
B40: Hosting of Customer's Information System Platforms/Systems/Components? / L'hébergement de systèmes/plateformes/composants du SI du client? | E40: No
B41: Website hosting for the Customer? / L'hébergement d'un site Web pour le client ? | E41: No
B42: Provision of SaaS based softwares? / La fourniture de logiciels en mode SaaS ? | E42: Yes
B43: Realization of IT development? / La réalisation de développements informatiques ? | E43: Yes
B44: Provision of managed security services or infrastructures services . Examples: NOC/SOC, telephony, internet connectivity, video conference / La fourniture de services de sécurité managés ou opérateur de services d'infrastructures Exemple : NOC/SOC, téléphonie, connectivité internet, video-conférence | E44: No
B45: Is the service provided occasional or short-termed? / La prestation est-elle ponctuelle ou de courte durée ? | E45: No
B46: Is the service provided mainly performed on Customer' site? / La prestation se déroule principalement dans les locaux du client ? | E46: No
A51: Z | B51: PST LIGHT | G51: =IF(AND(E46="No",E45="No",E44="No",E42="No",E41="No",E40="No",E37="No",G60="No",G64="No",E36="Yes without production access",OR('2 - Qualification'!F61="Low",'2 - Qualification'!F61="Medium"),'2 - Qualification'!F63="Not Required",'2 - Qualification'!J63="Not required"),TRUE,FALSE) -> FALSE | H51: =IF(G51=TRUE, "Z", "X") -> X
A52: A | B52: Consultancy/audit services, survey in any business or support activity (ex: marketing, medias, sales, finance, HR, IT, logistics, general services, architecture, decoration,…) which need exchange means and temporary storage (data, documents) to ensure communication with the Customer? / Des prestations de type études/conseils/audits/enquêtes dans tout domaine d'activité métier ou support ? (ex: marketing, médias, vente , finance, RH, IT, logistique, services généraux, architecture, décoration…) nécessitant notamment des moyens d’échange et de stockage temporaires d'information (documents, données) pour assurer la communication avec le Client. | G52: =IF(E36="Yes with production access","Yes",IF(E36="Yes without production access","Yes",IF(E36="No","No",0))) -> No | H52: =IF(G52= "Yes", "A", "X") -> X
A53: B | B53: Provider's connection to the client's network for maintenance, support and/or operation on non-IT technical components? Examples: on-site maintenance of electrical installation, air conditionning, shop lighting, CCTV, intrusion detection, remote maintenance of electrical installation, physical access control system management / Des connexions du prestataire à des fins de maintenance, support et/ou d'exploitation, sur des composants techniques non IT, mais raccordés au réseau du client ? Exemples : maintenance sur site installation électrique, climatisation, éclairage boutique, vidéosurveillance, détection intrusion, maintenance à distance installation électrique, gestion système de contrôle d'accès physique | G53: =IF(E37= "Yes", "Yes", "No") -> No | H53: =IF(G53= "Yes", "B", "X") -> X
A54: C | B54: Operational/Support/Maintenance intervention on IT ressources of the Customer? Examples: administration of systems, networks or databaseslocal user support, TMA, managed services / Des interventions d'exploitation, de support ou de maintenance sur le Système d'Information du client ? Exemples : administration de systèmes, réseaux ou bases de données sur site, support de proximité aux utilisateurs, TMA, Infogérance | G54: =IF(E38= "Yes", "Yes", "No") -> No | H54: =IF(G54= "Yes", "C", "X") -> X
A55: D | B55: Hosting of Customer's Information System Platforms/Systems/Components? / L'hébergement de systèmes/plateformes/composants du SI du client? | G55: =IF(E40= "Yes", "Yes", "No") -> No | H55: =IF(G55= "Yes", "D", "X") -> X
A56: E | B56: Website hosting for the Customer? / L'hébergement d'un site Web pour le client ? | G56: =IF(E41= "Yes", "Yes", "No") -> No | H56: =IF(G56= "Yes", "E", "X") -> X
A57: F | B57: Provision of SaaS based softwares? / La fourniture de logiciels en mode SaaS ? | G57: =IF(E42= "Yes", "Yes", "No") -> Yes | H57: =IF(G57= "Yes", "F", "X") -> F
A58: G | B58: Realization of IT development? / La réalisation de développements informatiques ? | G58: =IF(E43= "Yes", "Yes", "No") -> Yes | H58: =IF(G58= "Yes", "G", "X") -> G
A59: H | B59: Provision of managed security services or infrastructures services . Examples: NOC/SOC, telephony, internet connectivity, video conference / La fourniture de services de sécurité managés ou opérateur de services d'infrastructures Exemple : NOC/SOC, téléphonie, connectivité internet, video-conférence | G59: =IF(E44= "Yes", "Yes", "No") -> No | H59: =IF(G59= "Yes", "H", "X") -> X
A60: I | B60: Access to/Management of sensitive/confidential data? / L'accès ou la gestion par le prestataire de données sensibles ou stratégiques ? | G60: =IF(OR(COUNTIF('2 - Qualification'!C5:C12, "Yes"), E36="Yes with production access"), "Yes", "No") -> Yes | H60: =IF(G60="Yes", "I", "X") -> I | I60: Traité ailleurs
A61: J | B61: Access to/Management of personal data? / L'accès ou la gestion par le prestataire de données à caractère personnel ? | G61: =IF('2 - Qualification'!C15="Yes","Yes","No") -> No | H61: =IF(G61="Yes", "J", "X") -> X | I61: Traité ailleurs
A62: K | B62: Is the service provided occasional or short-termed? / La prestation est-elle ponctuelle ou de courte durée ? | G62: =IF(E45= "Yes", "Yes", "No") -> No | H62: =IF(G62= "Yes", "K", "X") -> X
A63: L | B63: Is the service provided mainly performed on Customer' site? / La prestation se déroule principalement dans les locaux du client ? | G63: =IF(E46= "Yes", "Yes", "No") -> No | H63: =IF(G63= "Yes", "L", "X") -> X
A64: M | B64: Does the service provided need a remote control to the Customer's Information System from the Provider' site? / La prestation nécessite une connexion à distance sur le Système d'Information du Client depuis les locaux du prestataire ? | G64: =IF(C13="Yes","Yes","No") -> Yes | H64: =IF(G64= "Yes", "M", "X") -> M | I64: Traité ailleurs

Sheet 2 - Qualification
B2: 1 - GENERAL DATA MAPPING
B3: Information management | G3: Application access management
B4: Type of information | C4: Yes/No | D4: WHERE the data will be stored ? | E4: Number of records | F4: WHO will access the information ? | G4: Profil name | H4: WHO will use the application ? | I4: Individual account ? | J4: Number of end users | K4: Description of profile rights and features
B5: Financial / Accounting | C5: Yes
B6: Legal
B7: Security (logs, configuration, etc)
B8: Commercial | C8: Yes
B9: Partner Information (B2B)
B10: Partner employee
B11: Employees Information | C11: Yes
B12: End Customer information (B2C) | C12: Yes
B13: Public data
B14: Other (give comments) | D14: Comments :
B15: Personal data
B16: Personal data : Type of information | E16: Yes/No | F16: Comments
B17: Civil status, identity, identification data | E17: Yes
B18: Physical appearance
B19: ID credentials (ID card number, passport, residence permit)
B20: Personal life (living habits, marital status, etc.)
B21: Professional life (résumé, education and professional training, awards, etc.)
B22: Economic and financial information (income, financial situation, tax situation, etc.)
B23: Connection data (IP addresses, event logs, etc.)
B24: Location data (travels, GPS data, GSM data, etc.)
B25: Social security number
B26: Biometric data
B27: Bank data (Credit card numbers)
B28: Philosophical, political, religious and trade-union views, sex life, health data, racial or ethnic origin, data concerning health or sex life
B29: Offenses, convictions, security measures
B30: Other sensitive personal data
B31: Data Retention Period | F31: 3rd Party: Sephora Legal - Contract:
B33: 2 - SECURITY ATTRIBUTES
B34: C (Confidentiality) | C34: I (Integrity) | E34: A (Availability) | G34: T (Traceability) | I34: P (Privacy) | K34: C (Compliance)
B35: 3 | C35: 3 | E35: 3 | G35: 2 | I35: 2 | K35: =IF(ISBLANK(I35),"Please complete the Privacy attribute",IF(I35=4,5,IF(I35=3,4,IF(I35=2,3,IF(I35=0,1,"Please check with gouvernance security teams to assess this attribute"))))) -> 3
B37: 3 - IMPACT ANALYSIS | N37: C (Confidentiality)
B38: Topics | E38: Options | F38: Comments | N38: 4 - Strictly Confidential | O38: Information is restricted above Confidential level, to a designated, named group of individuals on a strictly need to know basis. This also includes categories such as Privileged data and sensitive personal data ( health, salary, political affiliation, etc.) where Legal teams must be consulted.
B39: What would be the impact of data disclosure? | D39: To employees | N39: 3- Confidential | O39: Information is only available to a specific group of employees with a need to know – e.g. standard contracts or customer information. This also includes non-sensitive personal data.
D40: To a competitor | N40: 2- Internal | O40: Information is only available to INTERNAL’s employees & authorized external workers - e.g. training tools, policy, standards.
D41: To a supplier / sub-contractor | E41: 1 - Low | N41: 1- Public | O41: Public: information is available to the public - e.g. advertising, press releases.
D42: To the general public / Medias | N42: I (Integrity)
B43: What would be the impact if data integrity is affected ? | D43: Data is definitely lost | N43: 4- Enhanced | O43: No unauthorized modification tolerated
D44: Data is partailly damaged | N44: 3- Strong | O44: Any unauthorized modification of the information must be identified and automatically reverted
B45: If a production incident occurs, what would be the maximum acceptable data loss between the last backup the time of incident ? | D45: Recovery Point Objective | N45: 2- Medium | O45: Any unauthorized modification of the information must be identified
B46: If a production incident occurs, what would be the maximum duration of an unavailability acceptable by business teams ? | D46: Recovery Time Objective | N46: 1- Low | O46: No integrity required
B47: What would be the impact if you can't determine "who did what" (imputability of an operation) ? | D47: A posteriori in case of incident ? | N47: A (Availability) : Recovery Time Objective
D48: At any moment (real or near real time) ? | N48: 4- Very High | O48: 30 Min
N49: 3- High | O49: 24 Hours
B50: 4 - FEARED EVENTS | N50: 2-Medium | O50: 72 Hours
B51: In case of the compromission of the application, what are the business feared events that should be taken into account in security analysis | N51: 1-Low | O51: Best Effort
B52: Business data disclosure | D52: Yes/No | N52: T (Traceability)
B53: Personal information disclosure | D53: Yes/No | N53: 4- Very High | O53: Event related to authentication or right management on assets handing data or related to data modification must be traced, Logs are keept
B54: Internal fraud | D54: Yes/No | N54: 3- Detailed | O54: Event related to authentication or right management on assets handing data or related to data acess must be traced, Logs are keept
B55: External fraud | D55: Yes/No | N55: 2-Basic | O55: Event related to authentication or right management on assets handing data must be traced, Logs are keept
B56: Service availability or business disruption | D56: Yes/No | N56: 1-Low | O56: No traces required
B57: Loss of data integrity | D57: Yes/No | N57: P (Privacy)
B58: Other - Specific to the project | N58: 0 | O58: No personal information is handled
N59: 2 | O59: Identification data: email address,phone number, date of birth, gender…
B60: 5 - RESERVED TO GISEC TEAM | N60: 2 | O60: Personal life: lifestyle habits: wake up time, brightness, sound - noise, accelerometer data, temperature, humidity, particle levels …
B61: RISK ASSESSMENT | D61: =IF(I35=0,SUM(B35:G35)*K35*'1 - General description'!B16*'1 - General description'!D16,SUM(B35:G35)*I35*K35*'1 - General description'!B16*'1 - General description'!D16) -> 396 | E61: INHERENT RISK | F61: =IF(C64>=86,"Critical Risk",IF(C64>=60,"High Risk",IF(C64>=33,"Medium",IF(C64>0,"Low",0)))) -> Medium | I61: SENSITIVENESS | J61: =IF(D61>=2000,"Very Sensitive",IF(D61>=700,"Sensitive",IF(D61>=200,"Medium",IF(D61>0,"Low",0)))) -> Medium | N61: 2 | O61: Professional life ( resume, training, diplomas, awards...)
B62: Impact | C62: =B35+E35+K35+'1 - General description'!B16 -> 11 | N62: 3 | O62: Personal financial data (n°CB, RIB, income...)
B63: Likelyhood | C63: ='1 - General description'!B16+'1 - General description'!D16 -> 5 | E63: Data Privacy compliance | F63: =IF(C15="Yes","Required","Not Required") -> Not Required | I63: PCI-DSS Compliance | J63: =IF(E27="Yes","Required","Not Required") -> Not Required | N63: 3 | O63: Connection data (IP address, logs, cookies...)
B64: INHERENT RISK | C64: =C62*C63 -> 55 | N64: 3 | O64: Location data (movements, GPS data, GSM...)
N65: 3 | O65: Social Security Number, Unique Tax Number, Passport Number
B66: 6 - FUTURE | N66: 3 | O66: Data related to offences, convictions, security measures…
B67: NEXT STEPS | E67: TO DO | G67: STATUS | N67: 4 | O67: Biometric, genetic, health, life, image (photo/video) data
B68: Please review and apply standard security requirements | E68: ALWAYS | N68: 4 | O68: Data on racial or ethnic origin, political, philosophical or religious opinions
B69: Before any data is shared : work with Privacy/Legal team to ensure that NDA is signed. If needed put the relevant contract including privacy clause | E69: {=IF(OR(F5:F14="External Employee",F5:F14="Supplier"),"TO DO","Not Applicable")} -> Not Applicable | N69: C (Compliance)
B70: Assess the security level of the partner- 3rd party assessment (LVMH Questionaire) | E70: =IF(OR(F61="High Risk",F61="Medium"),"TO DO","Not Applicable") -> TO DO | N70: 5 | O70: Biometric, genetic, health, life, image (photo/video) data, Data on racial or ethnic origin, political, philosophical or religious opinions
B71: Budget & plan a penetration test | E71: {=IF(OR(F61="High Risk",'1 - General description'!C11:G11="Internet",'1 - General description'!C11:G11="Cloud/SaaS",'2 - Qualification'!C12="Yes"),"TO DO","Not Applicable")} -> TO DO | N71: 4 | O71: End customers sensitive personal information (Connection data , Social Security Number, etc.), Personal financial data (CB, payment terminal, etc.), Employees personal information (salary, n° CB, etc.)
B72: Engage with the Cyber security team to identify specific security requirements and architecture review | E72: =IF(OR(F61="High Risk",F61="Medium"),"TO DO","Not Applicable") -> TO DO | N72: 3 | O72: End customers Identification data (email address, phone number, date of birth, gender…) , confidential HR information, mandatory legal archiving (evidence to be used in court)
B73: Set up the Akamai WAF if the configuration of the partner WAF is not compliant | E73: =IF(OR('1 - General description'!G56="Yes",'1 - General description'!G57="Yes"),"TO DO","Not Applicable") -> TO DO | N73: 2 | O73: Professional Identification data: email address, phone number, date of birth, gender…, mandatory legal archiving (evidence to be used in audits/regulatory controls)
B74: Implement anti-bruteforce measures | E74: =IF(COUNTIF(H5:H13,"End Customer")>0,"TO DO","Not Applicable") -> Not Applicable | N74: 1 | O74: Legal archiving for internal controls
B75: Verify the compliance of the provider with our Data Privacy requirements, including the location of data centers in Europe. | E75: =IF(F63="Required","TO DO","Not Applicable") -> Not Applicable
B76: Request partner PCI-DSS attestation | E76: =IF(J63="Required","TO DO","Not Applicable") -> Not Applicable
B77: Check the versions of the communication protocols and encryption used | E77: =IF(OR('1 - General description'!G56="Yes",'1 - General description'!G57="Yes"),"TO DO","Not Applicable") -> TO DO
B78: Setup SSO Okta | E78: =IF(OR('1 - General description'!G57="Yes",'1 - General description'!C9="Stores"),"TO DO","Not Applicable") -> TO DO
B79: Formalize a rights matrix | E79: =IF('1 - General description'!G57="Yes","TO DO","Not Applicable") -> TO DO
B80: Check the implementation of the DMZ | E80: =IF(AND('1 - General description'!G57="Yes",'1 - General description'!F6="Yes"),"TO DO","Not Applicable") -> Not Applicable
B81: Customer data obfuscation | E81: =IF(OR('1 - General description'!G57="Yes",'1 - General description'!C9="Stores"),"TO DO","Not Applicable") -> TO DO
B82: Implement a secure method of data transfer (SFTP, GCP Bucket, OneDrive) | E82: =IF(ISNUMBER(SEARCH("Yes",'1 - General description'!E36)),"TO DO","Not Applicable") -> Not Applicable
B83: Other - Specific to the project Examples : Singl Sign On, Rights matrix, Data life cycle control, etc…

Sheet 3 - 3rd Party Security Policy
B1: 3 - THIRD PARTY SECURITY POLICY
B2: Chapter / Chapitre | C2: N° | D2: Title / Titre | E2: Description of the requirement / Description de l'exigence | F2: Use cases (*) / Cas d'usage (*) | G2: Applicability / Applicabilité | H2: Compliance / Conformité | I2: Detailed implemented measures / Détails sur les mesures implémentées | J2: Optional comment on non compliant or partially compliant controls / Commentaire éventuel sur les mesures non ou partiellement conformes
A3: 1 | B3: Framework for the contractual relationship / Cadrage de la relation contractuelle | C3: 1.1 | D3: Service provider’s Security Policy / Politique de Sécurité de la Société | E3: The service provider shall make its "Information System Security Policy" available to the client. / Le prestataire tient à la disposition du client sa « Politique de sécurité du système d'information ». | F3: B,C,D,E,F,G,H | G3: =IF(AND('1 - General description'!$G$51=FALSE, K3= TRUE),"Applicable","N.A") -> Applicable | K3: =OR(ISNUMBER(FIND('1 - General description'!$H$51,F3)),ISNUMBER(FIND('1 - General description'!$H$52,F3)),ISNUMBER(FIND('1 - General description'!$H$53,F3)),ISNUMBER(FIND('1 - General description'!$H$54,F3)),ISNUMBER(FIND('1 - General description'!$H$55,F3)),ISNUMBER(FIND('1 - General description'!$H$56,F3)),ISNUMBER(FIND('1 - General description'!$H$57,F3)),ISNUMBER(FIND('1 - General description'!$H$58,F3)),ISNUMBER(FIND('1 - General description'!$H$59,F3)),ISNUMBER(FIND('1 - General description'!$H$60,F3)),ISNUMBER(FIND('1 - General description'!$H$61,F3)),ISNUMBER(FIND('1 - General description'!$H$62,F3)),ISNUMBER(FIND('1 - General description'!$H$63,F3)),ISNUMBER(FIND('1 - General description'!$H$64,F3))) -> TRUE
A4: 1 | B4: Framework for the contractual relationship / Cadrage de la relation contractuelle | C4: 1.2 | D4: Certifications | E4: If the service provider claims to have security certifications, it will make it available to the client, specifying their scope, the expiry date, the identity of the certifying body, the date of the last audit and the conclusions of that audit. / Si le prestataire dispose de certifications en matière de sécurité et souhaite s'en prévaloir, il tiendra à la disposition du client ces certifications en précisant leur périmètre, la date d’expiration, l’identité de l’organisme certificateur, la date du dernier audit et les conclusions de cet audit. | F4: C,D,E,F,H | G4: =IF(AND('1 - General description'!$G$51=FALSE, K4= TRUE),"Applicable","N.A") -> Applicable | K4: =OR(ISNUMBER(FIND('1 - General description'!$H$51,F4)),ISNUMBER(FIND('1 - General description'!$H$52,F4)),ISNUMBER(FIND('1 - General description'!$H$53,F4)),ISNUMBER(FIND('1 - General description'!$H$54,F4)),ISNUMBER(FIND('1 - General description'!$H$55,F4)),ISNUMBER(FIND('1 - General description'!$H$56,F4)),ISNUMBER(FIND('1 - General description'!$H$57,F4)),ISNUMBER(FIND('1 - General description'!$H$58,F4)),ISNUMBER(FIND('1 - General description'!$H$59,F4)),ISNUMBER(FIND('1 - General description'!$H$60,F4)),ISNUMBER(FIND('1 - General description'!$H$61,F4)),ISNUMBER(FIND('1 - General description'!$H$62,F4)),ISNUMBER(FIND('1 - General description'!$H$63,F4)),ISNUMBER(FIND('1 - General description'!$H$64,F4))) -> TRUE
A5: 1 | B5: Framework for the contractual relationship / Cadrage de la relation contractuelle | C5: 1.3 | D5: Security Assurance Plan / Plan d'Assurance Sécurité | E5: The service provider shall submit a Security Assurance Plan (SAP) to the client which describes all of the security processes and solutions it will use to comply with the security requirements of the service provision. The SAP must be approved by the client and appended to the contract or order prior to the start of the contract. The Security Assurance Plan is a document subject to change over the life of the contract. The service provider shall submit any proposed changes for approval by the client. Such revisions of the SAP may be approved, for example, at the steering committees planned during the service delivery. The service provider undertakes to fulfil its security obligations in accordance with the Security Assurance Plan. The terms and conditions laid down by the SAP shall prevail over the service provider’s security documents. / Le prestataire soumet au client un Plan d’Assurance Sécurité (PAS) qui décrit l’ensemble des processus et dispositifs sécurité qu’elle met en œuvre pour respecter les exigences de sécurité de la prestation. Le PAS doit être approuvé par le client et annexé au contrat ou à la commande, préalablement au démarrage de la prestation. Le PAS est un document susceptible d'évoluer au cours de la prestation. Le prestataire soumet des propositions d’évolutions qui doivent être validées par le client. Ces révisions du PAS peuvent être validées par exemple à l’occasion des Comités prévus pour le pilotage de la prestation. Le prestataire s’engage à exécuter ses obligations vis-à-vis de la sécurité selon le PAS. Les conditions du PAS sont prioritaires par rapport aux documents de sécurité du prestataire. | F5: B, D, E, F, H | G5: =IF(AND('1 - General description'!$G$51=FALSE, K5= TRUE),"Applicable","N.A") -> Applicable | K5: =OR(ISNUMBER(FIND('1 - General description'!$H$51,F5)),ISNUMBER(FIND('1 - General description'!$H$52,F5)),ISNUMBER(FIND('1 - General description'!$H$53,F5)),ISNUMBER(FIND('1 - General description'!$H$54,F5)),ISNUMBER(FIND('1 - General description'!$H$55,F5)),ISNUMBER(FIND('1 - General description'!$H$56,F5)),ISNUMBER(FIND('1 - General description'!$H$57,F5)),ISNUMBER(FIND('1 - General description'!$H$58,F5)),ISNUMBER(FIND('1 - General description'!$H$59,F5)),ISNUMBER(FIND('1 - General description'!$H$60,F5)),ISNUMBER(FIND('1 - General description'!$H$61,F5)),ISNUMBER(FIND('1 - General description'!$H$62,F5)),ISNUMBER(FIND('1 - General description'!$H$63,F5)),ISNUMBER(FIND('1 - General description'!$H$64,F5))) -> TRUE
A6: 1 | B6: Framework for the contractual relationship / Cadrage de la relation contractuelle | C6: 1.4 | D6: Legal reminder : Duty to advise / Rappel légal : Devoir de Conseil | E6: The service provider shall be bound by a duty to advise and a duty to warn regarding security. In particular, whenever an operation is planned, it undertakes to notify the client of the security risks for data or for the IS and shall suggest measures to deal with such risks. This duty to advise shall be based on sound knowledge of the state of the art. External link : https://www.transatlantic-lawyer.com/the-obligation-of-information-and-the-duty-to-advise-in-contracts-under-french-law/ / Le prestataire est tenu à une obligation de conseil et de mise en garde en matière de sécurité. En particulier, lorsqu'une opération est envisagée, il s’engage à informer le client sur les risques vis-à-vis de la sécurité des données ou du SI et propose des actions pour traiter ces risques. Ce devoir de conseil s’appuie sur une bonne connaissance de l’état de l’art. Lien externe : https://www.droit-technologie.org/actualites/lobligation-dinformation-du-prestataire-informatique-a-legard-de-son-client/ | F6: B, C, D, E, F, H | G6: =IF(AND('1 - General description'!$G$51=FALSE, K6= TRUE),"Applicable","N.A") -> Applicable | K6: =OR(ISNUMBER(FIND('1 - General description'!$H$51,F6)),ISNUMBER(FIND('1 - General description'!$H$52,F6)),ISNUMBER(FIND('1 - General description'!$H$53,F6)),ISNUMBER(FIND('1 - General description'!$H$54,F6)),ISNUMBER(FIND('1 - General description'!$H$55,F6)),ISNUMBER(FIND('1 - General description'!$H$56,F6)),ISNUMBER(FIND('1 - General description'!$H$57,F6)),ISNUMBER(FIND('1 - General description'!$H$58,F6)),ISNUMBER(FIND('1 - General description'!$H$59,F6)),ISNUMBER(FIND('1 - General description'!$H$60,F6)),ISNUMBER(FIND('1 - General description'!$H$61,F6)),ISNUMBER(FIND('1 - General description'!$H$62,F6)),ISNUMBER(FIND('1 - General description'!$H$63,F6)),ISNUMBER(FIND('1 - General description'!$H$64,F6))) -> TRUE
A7: 2 | B7: Security related to Human Resources / Sécurité liée aux Ressources Humaines | C7: 2.1 | D7: Organisation | E7: The service provider appoints one or several privileged points of contacts on the security topics in the comment cell. Responsibility of this/these persons should covers: - Implementation of the security policy and processes - Protection against unauthorised access, data disclosure and the modification or destruction of content or systems - Reporting of potential or known security risks or incidents - Management of security incidents Any specific demand from the customer regarding security must be deatl with diligence and with according priority level by the service provider. / Le prestataire désigne un ou des points de contact privilégiés sur les aspects sécurité dans la case commentaire. Les responsabilités de cette ou ces personne(s) portent notamment sur : - La mise en œuvre de sa politique et de ses processus de sécurité ; - La protection contre des accès non autorisés, la divulgation de données, la modification ou la destruction de contenus ou de systèmes ; - La notification de failles présumées ou avérées de sécurité ; - La prise en charge des incidents de sécurité. Toute demande spécifique du client relative à la sécurité doit être traitée avec diligence et de manière prioritaire par le prestataire. | F7: B, C, D, E, F, H | G7: =IF(AND('1 - General description'!$G$51=FALSE, K7= TRUE),"Applicable","N.A") -> Applicable | K7: =OR(ISNUMBER(FIND('1 - General description'!$H$51,F7)),ISNUMBER(FIND('1 - General description'!$H$52,F7)),ISNUMBER(FIND('1 - General description'!$H$53,F7)),ISNUMBER(FIND('1 - General description'!$H$54,F7)),ISNUMBER(FIND('1 - General description'!$H$55,F7)),ISNUMBER(FIND('1 - General description'!$H$56,F7)),ISNUMBER(FIND('1 - General description'!$H$57,F7)),ISNUMBER(FIND('1 - General description'!$H$58,F7)),ISNUMBER(FIND('1 - General description'!$H$59,F7)),ISNUMBER(FIND('1 - General description'!$H$60,F7)),ISNUMBER(FIND('1 - General description'!$H$61,F7)),ISNUMBER(FIND('1 - General description'!$H$62,F7)),ISNUMBER(FIND('1 - General description'!$H$63,F7)),ISNUMBER(FIND('1 - General description'!$H$64,F7))) -> TRUE
A8: 2 | B8: Security related to Human Resources / Sécurité liée aux Ressources Humaines | C8: 2.2 | D8: Training / Formation | E8: The service provider shall ensure that its staff responsible for the service delivery receive training on the relevant tools and security processes. It shall also provide the client with a description of its training programme. / Le prestataire veille à ce que son personnel chargé de la prestation de services reçoive une formation sur les outils et les processus de sécurité. Il fournira également au client une description de son programme de formation. | F8: B, C, D, E, F, H | G8: =IF(AND('1 - General description'!$G$51=FALSE, K8= TRUE),"Applicable","N.A") -> Applicable | K8: =OR(ISNUMBER(FIND('1 - General description'!$H$51,F8)),ISNUMBER(FIND('1 - General description'!$H$52,F8)),ISNUMBER(FIND('1 - General description'!$H$53,F8)),ISNUMBER(FIND('1 - General description'!$H$54,F8)),ISNUMBER(FIND('1 - General description'!$H$55,F8)),ISNUMBER(FIND('1 - General description'!$H$56,F8)),ISNUMBER(FIND('1 - General description'!$H$57,F8)),ISNUMBER(FIND('1 - General description'!$H$58,F8)),ISNUMBER(FIND('1 - General description'!$H$59,F8)),ISNUMBER(FIND('1 - General description'!$H$60,F8)),ISNUMBER(FIND('1 - General description'!$H$61,F8)),ISNUMBER(FIND('1 - General description'!$H$62,F8)),ISNUMBER(FIND('1 - General description'!$H$63,F8)),ISNUMBER(FIND('1 - General description'!$H$64,F8))) -> TRUE
A9: 2 | B9: Security related to Human Resources / Sécurité liée aux Ressources Humaines | C9: 2.3 | D9: Awareness / Sensibilisation | E9: The service provider shall ensure that both its own staff and the staff of its subcontractors are fully informed and aware of the security requirements laid down by the contract. / Le prestataire veille à ce que son personnel et ceux de ses sous-traitants soient pleinement informés des exigences de sécurité contractuelles et soumis contractuellement à ces mêmes exigences. | F9: A, B, C, D, E, F, G, H, I, J, K, L, M, Z | G9: =IF(K9= TRUE,"Applicable","N.A") -> Applicable | K9: =OR(ISNUMBER(FIND('1 - General description'!$H$51,F9)),ISNUMBER(FIND('1 - General description'!$H$52,F9)),ISNUMBER(FIND('1 - General description'!$H$53,F9)),ISNUMBER(FIND('1 - General description'!$H$54,F9)),ISNUMBER(FIND('1 - General description'!$H$55,F9)),ISNUMBER(FIND('1 - General description'!$H$56,F9)),ISNUMBER(FIND('1 - General description'!$H$57,F9)),ISNUMBER(FIND('1 - General description'!$H$58,F9)),ISNUMBER(FIND('1 - General description'!$H$59,F9)),ISNUMBER(FIND('1 - General description'!$H$60,F9)),ISNUMBER(FIND('1 - General description'!$H$61,F9)),ISNUMBER(FIND('1 - General description'!$H$62,F9)),ISNUMBER(FIND('1 - General description'!$H$63,F9)),ISNUMBER(FIND('1 - General description'!$H$64,F9))) -> TRUE
A10: 2 | B10: Security related to Human Resources / Sécurité liée aux Ressources Humaines | C10: 2.4 | D10: Staff commitment / Engagement du personnel | E10: The service provider shall ensure that each member of its staff individually undertakes to keep the confidentiality of all types of sensitive information of which they may become aware when delivering the service. / Le prestataire garantit que ses personnels s’engagent individuellement à respecter la confidentialité de tout type d’information confidentielle qu’ils sont susceptibles de connaître dans le cadre de la prestation. | F10: Z | G10: =IF(K10= TRUE,"Applicable","N.A") -> N.A | K10: =OR(ISNUMBER(FIND('1 - General description'!$H$51,F10)),ISNUMBER(FIND('1 - General description'!$H$52,F10)),ISNUMBER(FIND('1 - General description'!$H$53,F10)),ISNUMBER(FIND('1 - General description'!$H$54,F10)),ISNUMBER(FIND('1 - General description'!$H$55,F10)),ISNUMBER(FIND('1 - General description'!$H$56,F10)),ISNUMBER(FIND('1 - General description'!$H$57,F10)),ISNUMBER(FIND('1 - General description'!$H$58,F10)),ISNUMBER(FIND('1 - General description'!$H$59,F10)),ISNUMBER(FIND('1 - General description'!$H$60,F10)),ISNUMBER(FIND('1 - General description'!$H$61,F10)),ISNUMBER(FIND('1 - General description'!$H$62,F10)),ISNUMBER(FIND('1 - General description'!$H$63,F10)),ISNUMBER(FIND('1 - General description'!$H$64,F10))) -> FALSE
A11: 2 | B11: Security related to Human Resources / Sécurité liée aux Ressources Humaines | C11: 2.4 | D11: Security Charter / Charte sécurité | E11: The service provider’s staff or the staff of its subcontractors carrying out work on the client’s premises shall comply with the client’s Security Charter during the period or their missions. / Les personnels du prestataire ou de ses sous-traitants intervenant dans les locaux du client se conforment à la charte sécurité du système d'information du client dans le cadre de l’exercice de leur mission. | F11: L | G11: =IF(AND('1 - General description'!$G$51=FALSE, K11= TRUE),"Applicable","N.A") -> N.A | K11: =OR(ISNUMBER(FIND('1 - General description'!$H$51,F11)),ISNUMBER(FIND('1 - General description'!$H$52,F11)),ISNUMBER(FIND('1 - General description'!$H$53,F11)),ISNUMBER(FIND('1 - General description'!$H$54,F11)),ISNUMBER(FIND('1 - General description'!$H$55,F11)),ISNUMBER(FIND('1 - General description'!$H$56,F11)),ISNUMBER(FIND('1 - General description'!$H$57,F11)),ISNUMBER(FIND('1 - General description'!$H$58,F11)),ISNUMBER(FIND('1 - General description'!$H$59,F11)),ISNUMBER(FIND('1 - General description'!$H$60,F11)),ISNUMBER(FIND('1 - General description'!$H$61,F11)),ISNUMBER(FIND('1 - General description'!$H$62,F11)),ISNUMBER(FIND('1 - General description'!$H$63,F11)),ISNUMBER(FIND('1 - General description'!$H$64,F11))) -> FALSE
A12: 2 | B12: Security related to Human Resources / Sécurité liée aux Ressources Humaines | C12: 2.5 | D12: Hosting agreement / Convention d'accueil | E12: If members of the staff of the service provider have to work on the client’s premises for a long period, a tripartite hosting agreement must be signed between the client, the service provider and each o these members. / En cas de mission de longue durée dans les locaux du client, une convention d’accueil tripartite doit être signée entre le client, le prestataire et chaque membre du personnel du prestataire intervenant sur le site du client. | F12: L | G12: =IF(AND('1 - General description'!$G$51=FALSE, K12= TRUE),"Applicable","N.A") -> N.A | K12: =OR(ISNUMBER(FIND('1 - General description'!$H$51,F12)),ISNUMBER(FIND('1 - General description'!$H$52,F12)),ISNUMBER(FIND('1 - General description'!$H$53,F12)),ISNUMBER(FIND('1 - General description'!$H$54,F12)),ISNUMBER(FIND('1 - General description'!$H$55,F12)),ISNUMBER(FIND('1 - General description'!$H$56,F12)),ISNUMBER(FIND('1 - General description'!$H$57,F12)),ISNUMBER(FIND('1 - General description'!$H$58,F12)),ISNUMBER(FIND('1 - General description'!$H$59,F12)),ISNUMBER(FIND('1 - General description'!$H$60,F12)),ISNUMBER(FIND('1 - General description'!$H$61,F12)),ISNUMBER(FIND('1 - General description'!$H$62,F12)),ISNUMBER(FIND('1 - General description'!$H$63,F12)),ISNUMBER(FIND('1 - General description'!$H$64,F12))) -> FALSE
A13: 2 | B13: Security related to Human Resources / Sécurité liée aux Ressources Humaines | C13: 2.6 | D13: Charter for Administrators / Charte administrateurs | E13: If members of the service provider’s staff has to use privileged accounts to access to the client’s information system, those members must sign the charter dedicated to administrators and privileged users. This charter is provided by the client. / Si les comptes informatiques utilisés par les personnels du prestataire pour accéder au système d'information du client sont des comptes à privilèges, alors ces personnels doivent signer la charte dédiée aux administrateurs et détenteurs de comptes à privilèges, communiquée par le client au prestataire. | F13: B, C, D, E, F, H, M | G13: =IF(K13= TRUE,"Applicable","N.A") -> Applicable | K13: =OR(ISNUMBER(FIND('1 - General description'!$H$51,F13)),ISNUMBER(FIND('1 - General description'!$H$52,F13)),ISNUMBER(FIND('1 - General description'!$H$53,F13)),ISNUMBER(FIND('1 - General description'!$H$54,F13)),ISNUMBER(FIND('1 - General description'!$H$55,F13)),ISNUMBER(FIND('1 - General description'!$H$56,F13)),ISNUMBER(FIND('1 - General description'!$H$57,F13)),ISNUMBER(FIND('1 - General description'!$H$58,F13)),ISNUMBER(FIND('1 - General description'!$H$59,F13)),ISNUMBER(FIND('1 - General description'!$H$60,F13)),ISNUMBER(FIND('1 - General description'!$H$61,F13)),ISNUMBER(FIND('1 - General description'!$H$62,F13)),ISNUMBER(FIND('1 - General description'!$H$63,F13)),ISNUMBER(FIND('1 - General description'!$H$64,F13))) -> TRUE
A14: 2 | B14: Security related to Human Resources / Sécurité liée aux Ressources Humaines | C14: 2.7 | D14: Display of service provider status / Affichage du statut de prestataire | E14: The service provider’s staff shall not introduce themselves as staff of the client when delivering the service, both at meetings, on their CV or on social media, for example. / Les personnels du prestataire ne doivent pas se présenter comme des personnels du client dans le cadre de leur mission pour le client, que ce soit lors de réunions, sur leur CV ou sur les réseaux sociaux, par exemple. | F14: L | G14: =IF(AND('1 - General description'!$G$51=FALSE, K14= TRUE),"Applicable","N.A") -> N.A | K14: =OR(ISNUMBER(FIND('1 - General description'!$H$51,F14)),ISNUMBER(FIND('1 - General description'!$H$52,F14)),ISNUMBER(FIND('1 - General description'!$H$53,F14)),ISNUMBER(FIND('1 - General description'!$H$54,F14)),ISNUMBER(FIND('1 - General description'!$H$55,F14)),ISNUMBER(FIND('1 - General description'!$H$56,F14)),ISNUMBER(FIND('1 - General description'!$H$57,F14)),ISNUMBER(FIND('1 - General description'!$H$58,F14)),ISNUMBER(FIND('1 - General description'!$H$59,F14)),ISNUMBER(FIND('1 - General description'!$H$60,F14)),ISNUMBER(FIND('1 - General description'!$H$61,F14)),ISNUMBER(FIND('1 - General description'!$H$62,F14)),ISNUMBER(FIND('1 - General description'!$H$63,F14)),ISNUMBER(FIND('1 - General description'!$H$64,F14))) -> FALSE
A15: 2 | B15: Security related to Human Resources / Sécurité liée aux Ressources Humaines | C15: 2.8 | D15: Subcontracting / Sous-traitance | E15: The service provider shall not use any subcontractors without the explicit consent of the client. The client reserves the right to reject a subcontractor if it does not meet the client’s security requirements. The use of a subcontractor must not reduce the level of security governed by the scope of the contract entered into with the client. In all cases, the service provider shall accept sole liability to the client for any breaches of security within that scope and undertakes to subject any subcontractors to obligations similar to those laid down in the contract, wherever these are applicable. / Le prestataire ne peut recourir à un sous-traitant sans l’accord écrit et préalable du client. Le client se réserve la possibilité de refuser un sous-traitant si celui-ci ne répond pas aux exigences de sécurité du client. Le recours à ce sous-traitant ne doit pas être de nature à réduire le niveau de sécurité du périmètre objet du contrat avec le client. Dans tous les cas, le prestataire reste seul responsable vis-à-vis du client des atteintes à la sécurité sur ce périmètre et s'engage à soumettre ses éventuels sous-traitants à des obligations similaires à celles contenues dans le contrat, sous réserve de leur applicabilité (notamment les obligations relatives à la sécurité, la confidentialité, la protection des données, l'audit et l'assurance). | F15: A, B, C, D, E, F, G, H, I, J, K, L, M | G15: =IF(AND('1 - General description'!$G$51=FALSE, K15= TRUE),"Applicable","N.A") -> Applicable | K15: =OR(ISNUMBER(FIND('1 - General description'!$H$51,F15)),ISNUMBER(FIND('1 - General description'!$H$52,F15)),ISNUMBER(FIND('1 - General description'!$H$53,F15)),ISNUMBER(FIND('1 - General description'!$H$54,F15)),ISNUMBER(FIND('1 - General description'!$H$55,F15)),ISNUMBER(FIND('1 - General description'!$H$56,F15)),ISNUMBER(FIND('1 - General description'!$H$57,F15)),ISNUMBER(FIND('1 - General description'!$H$58,F15)),ISNUMBER(FIND('1 - General description'!$H$59,F15)),ISNUMBER(FIND('1 - General description'!$H$60,F15)),ISNUMBER(FIND('1 - General description'!$H$61,F15)),ISNUMBER(FIND('1 - General description'!$H$62,F15)),ISNUMBER(FIND('1 - General description'!$H$63,F15)),ISNUMBER(FIND('1 - General description'!$H$64,F15))) -> TRUE
A16: 3 | B16: Confidentiality / Confidentialité | C16: 3.1 | D16: Autorisations | E16: The access rights of the service provider’s staff to the platforms it makes available to the client must be clearly defined, communicated to and approved by the client. The same shall apply to all access to the programs and content that the client installs, produces and uses on those platforms. / Les droits d’accès des personnels du prestataire aux plates-formes qu’elle met à disposition du client doivent être précisément définis, communiqués au client et validés par celui-ci. Il en est de même pour les accès éventuels aux programmes et aux contenus que le client va installer, produire et exploiter sur ces plates-formes. | F16: B, C, D, E, F, H | G16: =IF(AND('1 - General description'!$G$51=FALSE, K16= TRUE),"Applicable","N.A") -> Applicable | K16: =OR(ISNUMBER(FIND('1 - General description'!$H$51,F16)),ISNUMBER(FIND('1 - General description'!$H$52,F16)),ISNUMBER(FIND('1 - General description'!$H$53,F16)),ISNUMBER(FIND('1 - General description'!$H$54,F16)),ISNUMBER(FIND('1 - General description'!$H$55,F16)),ISNUMBER(FIND('1 - General description'!$H$56,F16)),ISNUMBER(FIND('1 - General description'!$H$57,F16)),ISNUMBER(FIND('1 - General description'!$H$58,F16)),ISNUMBER(FIND('1 - General description'!$H$59,F16)),ISNUMBER(FIND('1 - General description'!$H$60,F16)),ISNUMBER(FIND('1 - General description'!$H$61,F16)),ISNUMBER(FIND('1 - General description'!$H$62,F16)),ISNUMBER(FIND('1 - General description'!$H$63,F16)),ISNUMBER(FIND('1 - General description'!$H$64,F16))) -> TRUE
A17: 3 | B17: Confidentiality / Confidentialité | C17: 3.2 | D17: Confidentiality agreement / Engagement de confidentialité | E17: The service provider shall take all necessary measures to ensure that none of the client’s content is disclosed to any unauthorised individual or legal entity. This obligation applies to all content, irrespective of the medium or nature, handled or exchanged when delivering the service. The confidentiality obligation also concerns all information of which disclosure is deemed to be a threat to the security of the system (passwords, data encryption keys and documentation regarding system architecture and security, etc.). / Le prestataire s’engage à mettre tout en œuvre pour que les contenus du client ne soient pas divulgués à des personnes physiques ou morales non autorisées. Cet engagement concerne tous les contenus quel qu’en soit le support ou la nature, manipulés ou échangés dans le cadre de la prestation. L’engagement de confidentialité concerne aussi toute information dont la divulgation est de nature à porter atteinte à la sécurité du système (mots de passe, clés de chiffrement, documentations relative à l’architecture et la sécurité du système, etc.). | F17: A, B, C, D, E, F, G, H, I, J, K, L, M, Z | G17: =IF(K17= TRUE,"Applicable","N.A") -> Applicable | K17: =OR(ISNUMBER(FIND('1 - General description'!$H$51,F17)),ISNUMBER(FIND('1 - General description'!$H$52,F17)),ISNUMBER(FIND('1 - General description'!$H$53,F17)),ISNUMBER(FIND('1 - General description'!$H$54,F17)),ISNUMBER(FIND('1 - General description'!$H$55,F17)),ISNUMBER(FIND('1 - General description'!$H$56,F17)),ISNUMBER(FIND('1 - General description'!$H$57,F17)),ISNUMBER(FIND('1 - General description'!$H$58,F17)),ISNUMBER(FIND('1 - General description'!$H$59,F17)),ISNUMBER(FIND('1 - General description'!$H$60,F17)),ISNUMBER(FIND('1 - General description'!$H$61,F17)),ISNUMBER(FIND('1 - General description'!$H$62,F17)),ISNUMBER(FIND('1 - General description'!$H$63,F17)),ISNUMBER(FIND('1 - General description'!$H$64,F17))) -> TRUE
A18: 3 | B18: Confidentiality / Confidentialité | C18: 3.3 | D18: Disclosure to third parties / Communication à un tiers | E18: The service provider is not authorised to transfer any data or information about the contract, or obtained in connection with the delivery of the contract, to any third parties without the prior explicit consent of the client. / Le prestataire n’est pas autorisé à transférer des données ou des informations relatives au contrat ou obtenues dans le cadre de l’exercice du contrat à un tiers sans une autorisation préalable explicite du client. | F18: Z | G18: =IF(K18= TRUE,"Applicable","N.A") -> N.A | K18: =OR(ISNUMBER(FIND('1 - General description'!$H$51,F18)),ISNUMBER(FIND('1 - General description'!$H$52,F18)),ISNUMBER(FIND('1 - General description'!$H$53,F18)),ISNUMBER(FIND('1 - General description'!$H$54,F18)),ISNUMBER(FIND('1 - General description'!$H$55,F18)),ISNUMBER(FIND('1 - General description'!$H$56,F18)),ISNUMBER(FIND('1 - General description'!$H$57,F18)),ISNUMBER(FIND('1 - General description'!$H$58,F18)),ISNUMBER(FIND('1 - General description'!$H$59,F18)),ISNUMBER(FIND('1 - General description'!$H$60,F18)),ISNUMBER(FIND('1 - General description'!$H$61,F18)),ISNUMBER(FIND('1 - General description'!$H$62,F18)),ISNUMBER(FIND('1 - General description'!$H$63,F18)),ISNUMBER(FIND('1 - General description'!$H$64,F18))) -> FALSE
A19: 4 | B19: Identity and access management / Gestion des identités et des accès | C19: 4.1 | D19: Remote access to the client's information system / Accès distant au système d'information du Client | E19: In cases where remote operations are carried out by the service provider on the client’s resources , the service provider will always use nominative accounts allocated by the client. These accounts will be created on demand by the service provider. It must provide a list of the members of staff concerned and notify the client whenever a member of staff leaves, or whenever a new member of staff is allocated to the service. These accounts are strictly limited to a personal use and the service provider is responsaible of ensuring that these accounts will not be shared among its staff. / Dans le cas d’opérations réalisées à distance par le prestataire sur les systèmes d'information du client, le prestataire n'utilisera que des comptes nominatifs. Ces comptes pourront être créé sur demande du prestataire. Il devra fournir la liste des personnels concernés et informer le client dès qu’un personnel quitte la prestation ou le prestataire, ou dès qu’un nouveau personnel est affecté à la prestation. Ces comptes sont à usage strictement personnel et le prestataire est responsable de s'assurer que ces comptes ne seront pas partagés entre ses personnels. | F19: A, C, I, J, M | G19: =IF(AND('1 - General description'!$G$51=FALSE, K19= TRUE),"Applicable","N.A") -> Applicable | K19: =OR(ISNUMBER(FIND('1 - General description'!$H$51,F19)),ISNUMBER(FIND('1 - General description'!$H$52,F19)),ISNUMBER(FIND('1 - General description'!$H$53,F19)),ISNUMBER(FIND('1 - General description'!$H$54,F19)),ISNUMBER(FIND('1 - General description'!$H$55,F19)),ISNUMBER(FIND('1 - General description'!$H$56,F19)),ISNUMBER(FIND('1 - General description'!$H$57,F19)),ISNUMBER(FIND('1 - General description'!$H$58,F19)),ISNUMBER(FIND('1 - General description'!$H$59,F19)),ISNUMBER(FIND('1 - General description'!$H$60,F19)),ISNUMBER(FIND('1 - General description'!$H$61,F19)),ISNUMBER(FIND('1 - General description'!$H$62,F19)),ISNUMBER(FIND('1 - General description'!$H$63,F19)),ISNUMBER(FIND('1 - General description'!$H$64,F19))) -> TRUE
A20: 4 | B20: Identity and access management / Gestion des identités et des accès | C20: 4.2 | D20: Revocation of accounts / Déprovisionnement des comptes | E20: The service provider shall ensure that anyone who is no longer part of its staff ceases to hold active accounts which might be used to access the client’s resources or the platforms made available to the client. / Le prestataire veille à ce que les personnes qui ne font plus partie de son personnel ne possèdent plus, au moment de leur départ de la société, de comptes actifs susceptibles d’être utilisés pour un accès au système d'information du client ou à des plates-formes mises à disposition du client. | F20: B, C, D, E, F, H, Z | G20: =IF(K20= TRUE,"Applicable","N.A") -> Applicable | K20: =OR(ISNUMBER(FIND('1 - General description'!$H$51,F20)),ISNUMBER(FIND('1 - General description'!$H$52,F20)),ISNUMBER(FIND('1 - General description'!$H$53,F20)),ISNUMBER(FIND('1 - General description'!$H$54,F20)),ISNUMBER(FIND('1 - General description'!$H$55,F20)),ISNUMBER(FIND('1 - General description'!$H$56,F20)),ISNUMBER(FIND('1 - General description'!$H$57,F20)),ISNUMBER(FIND('1 - General description'!$H$58,F20)),ISNUMBER(FIND('1 - General description'!$H$59,F20)),ISNUMBER(FIND('1 - General description'!$H$60,F20)),ISNUMBER(FIND('1 - General description'!$H$61,F20)),ISNUMBER(FIND('1 - General description'!$H$62,F20)),ISNUMBER(FIND('1 - General description'!$H$63,F20)),ISNUMBER(FIND('1 - General description'!$H$64,F20))) -> TRUE
A21: 4 | B21: Identity and access management / Gestion des identités et des accès | C21: 4.3 | D21: Staff identification / Identification du personnel | E21: A list of the client’s members of staff authorised to request services from the service provider shall be drawn up together with a means of authenticating those persons. This rule shall also apply to the service provider’s members of staff who need to contact the client’s members of staff – for example, for validation purposes or regarding operations that the service provider needs to carry out. The service provider shall create and regularly update a list of members of staff authorised to access the client’s data and/or to interact with the client’s resources, together with their level of authorisation (access types and client’s resources concerned). This list shall be made available to the client. / La liste des personnels du client autorisés à solliciter des services auprès du prestataire est définie ainsi qu'un moyen d'authentification de ces personnels. Cette règle s'applique réciproquement pour les personnels du prestataire qui doivent solliciter des personnels du client, par exemple à des fins de validation pour des opérations que doit mener le prestataire. Le prestataire élabore et met à jour régulièrement une liste des personnels autorisés à accéder aux données du client et/ou à intervenir sur les ressources du client ainsi que leur niveau d’habilitation (types d’accès et ressources concernées du client). Cette liste est tenue à la disposition du client. | F21: A, B, C, D, E, F, G, H, I, J, K, L, M | G21: =IF(AND('1 - General description'!$G$51=FALSE, K21= TRUE),"Applicable","N.A") -> Applicable | K21: =OR(ISNUMBER(FIND('1 - General description'!$H$51,F21)),ISNUMBER(FIND('1 - General description'!$H$52,F21)),ISNUMBER(FIND('1 - General description'!$H$53,F21)),ISNUMBER(FIND('1 - General description'!$H$54,F21)),ISNUMBER(FIND('1 - General description'!$H$55,F21)),ISNUMBER(FIND('1 - General description'!$H$56,F21)),ISNUMBER(FIND('1 - General description'!$H$57,F21)),ISNUMBER(FIND('1 - General description'!$H$58,F21)),ISNUMBER(FIND('1 - General description'!$H$59,F21)),ISNUMBER(FIND('1 - General description'!$H$60,F21)),ISNUMBER(FIND('1 - General description'!$H$61,F21)),ISNUMBER(FIND('1 - General description'!$H$62,F21)),ISNUMBER(FIND('1 - General description'!$H$63,F21)),ISNUMBER(FIND('1 - General description'!$H$64,F21))) -> TRUE
A22: 4 | B22: Identity and access management / Gestion des identités et des accès | C22: 4.4 | D22: Segregation of duties / Ségrégation des tâches | E22: The service provider shall implement strict management of the separation of duties when allocating access rights to its staff. / Le prestataire met en œuvre une gestion rigoureuse de la ségrégation des tâches dans l'attribution des droits d'accès pour ses personnels. | F22: D, E, F, H | G22: =IF(AND('1 - General description'!$G$51=FALSE, K22= TRUE),"Applicable","N.A") -> Applicable | K22: =OR(ISNUMBER(FIND('1 - General description'!$H$51,F22)),ISNUMBER(FIND('1 - General description'!$H$52,F22)),ISNUMBER(FIND('1 - General description'!$H$53,F22)),ISNUMBER(FIND('1 - General description'!$H$54,F22)),ISNUMBER(FIND('1 - General description'!$H$55,F22)),ISNUMBER(FIND('1 - General description'!$H$56,F22)),ISNUMBER(FIND('1 - General description'!$H$57,F22)),ISNUMBER(FIND('1 - General description'!$H$58,F22)),ISNUMBER(FIND('1 - General description'!$H$59,F22)),ISNUMBER(FIND('1 - General description'!$H$60,F22)),ISNUMBER(FIND('1 - General description'!$H$61,F22)),ISNUMBER(FIND('1 - General description'!$H$62,F22)),ISNUMBER(FIND('1 - General description'!$H$63,F22)),ISNUMBER(FIND('1 - General description'!$H$64,F22))) -> TRUE
A23: 4 | B23: Identity and access management / Gestion des identités et des accès | C23: 4.5 | D23: Password management / Gestion des mots de passe | E23: The service provider’s staff shall use strong passwords: minimum 12 characters for standard accounts and minimum 16 characters for privileged accounts. Passwords shall be changed at least every ninety (90) days. Passwords must be complex and contain at least letters, numbers and special characters. The service provider’s members of staff undertake never to ask the client’s employees for their password when carrying out their work. If a user’s password is required in order to carry out a particular operation, the service provider’s staff must ask the user concerned to enter their password personally. The service provider undertakes to ensure that the accounts and passwords used by its staff concerning specificly the client’s resources are specific to the client, and thus different from the accounts and passwords used for its other clients. Every equipment subject to remote monitoring or remote maintenance must have an account which is reserved for that purpose and for which the identification and authentication parameters are different from those of all other equipment. / Les personnels du prestataire utilisent des mots de passe robustes : 12 caractères a minima pour des comptes standard, 16 caractères minima pour des comptes à privilèges. L’âge de ces mots de passe n'excéde pas 90 jours. Ces mots de passe sont complexes et comportent a minima des lettres, chiffres et caractères spéciaux. Les personnels du prestataire s’engagent à ne jamais demander leur mot de passe à des personnels du client, dans le cadre de leurs interventions. Par exemple, si la saisie d’un mot de passe d’un utilisateur est nécessaire pour mener à bien une intervention, les personnels du prestataire peuvent demander à l’utilisateur concerné de saisir lui-même son mot de passe. Le prestataire s’engage à ce que les comptes et mots de passe utilisés par ses personnels et concernant spécifiquement le système d'information du client soient dédiés au client, donc différents des comptes et mots de passe utilisés pour ses autres clients. Chaque équipement objet d’une télésurveillance ou d’une télémaintenance doit disposer d’un compte réservé à cette fin et dont les paramètres d’identification et d’authentification sont différents de ceux de tout autre équipement. | F23: A, B, C, D, E, F, M, Z | G23: =IF(K23= TRUE,"Applicable","N.A") -> Applicable | K23: =OR(ISNUMBER(FIND('1 - General description'!$H$51,F23)),ISNUMBER(FIND('1 - General description'!$H$52,F23)),ISNUMBER(FIND('1 - General description'!$H$53,F23)),ISNUMBER(FIND('1 - General description'!$H$54,F23)),ISNUMBER(FIND('1 - General description'!$H$55,F23)),ISNUMBER(FIND('1 - General description'!$H$56,F23)),ISNUMBER(FIND('1 - General description'!$H$57,F23)),ISNUMBER(FIND('1 - General description'!$H$58,F23)),ISNUMBER(FIND('1 - General description'!$H$59,F23)),ISNUMBER(FIND('1 - General description'!$H$60,F23)),ISNUMBER(FIND('1 - General description'!$H$61,F23)),ISNUMBER(FIND('1 - General description'!$H$62,F23)),ISNUMBER(FIND('1 - General description'!$H$63,F23)),ISNUMBER(FIND('1 - General description'!$H$64,F23))) -> TRUE
A24: 4 | B24: Identity and access management / Gestion des identités et des accès | C24: 4.6 | D24: Single Sign-On Authentication / Authentification Single Sign-On | E24: Single Sign-On (SSO) authentication must be configured with the Sephora (or LVMH group’s) SSO instance, based on the Okta solution. All solutions provided as part of the service, on which Sephora users authenticate via a Sephora email address, must therefore be compatible with Okta, SAML or OpenID Connect protocols. / L’authentification Single Sign-On (SSO) doit être configurée avec l’instance SSO de Sephora (ou du groupe LVMH), basée sur la solution Okta. Toutes les solutions fournies dans le cadre du service, sur lesquelles des utilisateurs Sephora s’authentifient via une adresse email Sephora, doivent donc être compatibles avec les protocoles Okta, SAML ou OpenID Connect. | F24: E, F, G | G24: =IF(AND('1 - General description'!$G$51=FALSE, K24= TRUE),"Applicable","N.A") -> Applicable | K24: =OR(ISNUMBER(FIND('1 - General description'!$H$51,F24)),ISNUMBER(FIND('1 - General description'!$H$52,F24)),ISNUMBER(FIND('1 - General description'!$H$53,F24)),ISNUMBER(FIND('1 - General description'!$H$54,F24)),ISNUMBER(FIND('1 - General description'!$H$55,F24)),ISNUMBER(FIND('1 - General description'!$H$56,F24)),ISNUMBER(FIND('1 - General description'!$H$57,F24)),ISNUMBER(FIND('1 - General description'!$H$58,F24)),ISNUMBER(FIND('1 - General description'!$H$59,F24)),ISNUMBER(FIND('1 - General description'!$H$60,F24)),ISNUMBER(FIND('1 - General description'!$H$61,F24)),ISNUMBER(FIND('1 - General description'!$H$62,F24)),ISNUMBER(FIND('1 - General description'!$H$63,F24)),ISNUMBER(FIND('1 - General description'!$H$64,F24))) -> TRUE
A25: 4 | B25: Identity and access management / Gestion des identités et des accès | C25: 4.7 | D25: Default accounts and passwords / Comptes et mots de passe par défaut | E25: All default privileged accounts amust be disabled, deleted or renamed. A least, default passwords associated with these accounts must be replaced by strong passords meeting rule 5.8. Storage of these passwords must be secure (ex: electronic safe solution). / Tous les comptes à privilèges par défaut doivent être supprimés, désactivés ou renommés. A minima les mots de passe par défaut associés à ces comptes doivent être remplacés par des mots de passe conformes à la règle "Gestion des mots de passe". Le stockage de ces mots de passe doit être fait de façon sécurisée (par exemple : coffre-fort logiciel à mots de passe). | F25: B, C, D, E, F, M | G25: =IF(AND('1 - General description'!$G$51=FALSE, K25= TRUE),"Applicable","N.A") -> Applicable | K25: =OR(ISNUMBER(FIND('1 - General description'!$H$51,F25)),ISNUMBER(FIND('1 - General description'!$H$52,F25)),ISNUMBER(FIND('1 - General description'!$H$53,F25)),ISNUMBER(FIND('1 - General description'!$H$54,F25)),ISNUMBER(FIND('1 - General description'!$H$55,F25)),ISNUMBER(FIND('1 - General description'!$H$56,F25)),ISNUMBER(FIND('1 - General description'!$H$57,F25)),ISNUMBER(FIND('1 - General description'!$H$58,F25)),ISNUMBER(FIND('1 - General description'!$H$59,F25)),ISNUMBER(FIND('1 - General description'!$H$60,F25)),ISNUMBER(FIND('1 - General description'!$H$61,F25)),ISNUMBER(FIND('1 - General description'!$H$62,F25)),ISNUMBER(FIND('1 - General description'!$H$63,F25)),ISNUMBER(FIND('1 - General description'!$H$64,F25))) -> TRUE
A26: 5 | B26: Traceability / Traçabilité | C26: 5.1 | D26: Logging / Activation des traces | E26: Logging shall be enabled on all components implemented or accessed by the service provider. Events will be recorded and timestamped in those logs. / Une journalisation est activée sur tous les composants mis en œuvre ou accédés par le prestataire. Les événements sont enregistrés et horodatés dans ces journaux. | F26: C, D, E, F, H | G26: =IF(AND('1 - General description'!$G$51=FALSE, K26= TRUE),"Applicable","N.A") -> Applicable | K26: =OR(ISNUMBER(FIND('1 - General description'!$H$51,F26)),ISNUMBER(FIND('1 - General description'!$H$52,F26)),ISNUMBER(FIND('1 - General description'!$H$53,F26)),ISNUMBER(FIND('1 - General description'!$H$54,F26)),ISNUMBER(FIND('1 - General description'!$H$55,F26)),ISNUMBER(FIND('1 - General description'!$H$56,F26)),ISNUMBER(FIND('1 - General description'!$H$57,F26)),ISNUMBER(FIND('1 - General description'!$H$58,F26)),ISNUMBER(FIND('1 - General description'!$H$59,F26)),ISNUMBER(FIND('1 - General description'!$H$60,F26)),ISNUMBER(FIND('1 - General description'!$H$61,F26)),ISNUMBER(FIND('1 - General description'!$H$62,F26)),ISNUMBER(FIND('1 - General description'!$H$63,F26)),ISNUMBER(FIND('1 - General description'!$H$64,F26))) -> TRUE
A27: 5 | B27: Traceability / Traçabilité | C27: 5.2 | D27: Minimal content of the logs / Contenu minimal des traces | E27: Logs shall contain type of operation (connection, file access…), user identification, network address, date and time, failed operations and component involved. / Le détail des traces capturées contient le type d'activité réalisée (ouverture de session, accès à un fichier,…), l'identification de l'utilisateur, l'adresse réseau, la date et l'heure, les échecs et les composants système ou applicatif affecté. | F27: C, D, E, F, H | G27: =IF(AND('1 - General description'!$G$51=FALSE, K27= TRUE),"Applicable","N.A") -> Applicable | K27: =OR(ISNUMBER(FIND('1 - General description'!$H$51,F27)),ISNUMBER(FIND('1 - General description'!$H$52,F27)),ISNUMBER(FIND('1 - General description'!$H$53,F27)),ISNUMBER(FIND('1 - General description'!$H$54,F27)),ISNUMBER(FIND('1 - General description'!$H$55,F27)),ISNUMBER(FIND('1 - General description'!$H$56,F27)),ISNUMBER(FIND('1 - General description'!$H$57,F27)),ISNUMBER(FIND('1 - General description'!$H$58,F27)),ISNUMBER(FIND('1 - General description'!$H$59,F27)),ISNUMBER(FIND('1 - General description'!$H$60,F27)),ISNUMBER(FIND('1 - General description'!$H$61,F27)),ISNUMBER(FIND('1 - General description'!$H$62,F27)),ISNUMBER(FIND('1 - General description'!$H$63,F27)),ISNUMBER(FIND('1 - General description'!$H$64,F27))) -> TRUE
A28: 5 | B28: Traceability / Traçabilité | C28: 5.3 | D28: Type of event logged / Type d'événement tracé | E28: Logging strategy enables to get the following events : individual user accesses, rejected accesses to systems, files or data, privileged accesses, configuration changes, authorizations changes, data removal, activation or deactivation of security components. / La stratégie de traçabilité permet de récupérer les évènements suivants : les accès utilisateurs individuels, tentatives d'accès rejetées au système, à l'application, au fichier ou aux données applicatives, les accès à privilèges, les changements de configuration système ou applicative, le changement des niveaux d'habilitation, la suppression de données, l'activation ou la désactivation des système de sécurité. | F28: C, D, E, F, H | G28: =IF(AND('1 - General description'!$G$51=FALSE, K28= TRUE),"Applicable","N.A") -> Applicable | K28: =OR(ISNUMBER(FIND('1 - General description'!$H$51,F28)),ISNUMBER(FIND('1 - General description'!$H$52,F28)),ISNUMBER(FIND('1 - General description'!$H$53,F28)),ISNUMBER(FIND('1 - General description'!$H$54,F28)),ISNUMBER(FIND('1 - General description'!$H$55,F28)),ISNUMBER(FIND('1 - General description'!$H$56,F28)),ISNUMBER(FIND('1 - General description'!$H$57,F28)),ISNUMBER(FIND('1 - General description'!$H$58,F28)),ISNUMBER(FIND('1 - General description'!$H$59,F28)),ISNUMBER(FIND('1 - General description'!$H$60,F28)),ISNUMBER(FIND('1 - General description'!$H$61,F28)),ISNUMBER(FIND('1 - General description'!$H$62,F28)),ISNUMBER(FIND('1 - General description'!$H$63,F28)),ISNUMBER(FIND('1 - General description'!$H$64,F28))) -> TRUE
A29: 5 | B29: Traceability / Traçabilité | C29: 5.4 | D29: Use and retention of logs / Exploitation et rétention des traces | E29: The client will be able to retrieve and use logs either: - In real time, or near real-time OR - On demand. In all cases, the service provider shall retain logs for a period of no less than six (6) months. / Les traces sont récupérables et exploitables par le client soit : - En temps réel ou quasi en temps réel - À la demande. Dans tous les cas, la conservation des traces par le prestataire est assurée avec une antériorité qui ne saurait être inférieure à 6 mois. | F29: C, D, E, F, H | G29: =IF(AND('1 - General description'!$G$51=FALSE, K29= TRUE),"Applicable","N.A") -> Applicable | K29: =OR(ISNUMBER(FIND('1 - General description'!$H$51,F29)),ISNUMBER(FIND('1 - General description'!$H$52,F29)),ISNUMBER(FIND('1 - General description'!$H$53,F29)),ISNUMBER(FIND('1 - General description'!$H$54,F29)),ISNUMBER(FIND('1 - General description'!$H$55,F29)),ISNUMBER(FIND('1 - General description'!$H$56,F29)),ISNUMBER(FIND('1 - General description'!$H$57,F29)),ISNUMBER(FIND('1 - General description'!$H$58,F29)),ISNUMBER(FIND('1 - General description'!$H$59,F29)),ISNUMBER(FIND('1 - General description'!$H$60,F29)),ISNUMBER(FIND('1 - General description'!$H$61,F29)),ISNUMBER(FIND('1 - General description'!$H$62,F29)),ISNUMBER(FIND('1 - General description'!$H$63,F29)),ISNUMBER(FIND('1 - General description'!$H$64,F29))) -> TRUE
A30: 5 | B30: Traceability / Traçabilité | C30: 5.5 | D30: Provision of logs / Mise à disposition des traces | E30: In the case of on-demand access, the service provider must provide the client with the logs or extracts from the logs within a period agreed in the contract. If the demands comes within the frame of an investigation caused by a security incident, the service provider will work diligently with a priority level adapted to the emergency of the situation caused by the incident. / Dans le cas d’un accès à la demande, des traces ou des extraits des traces doivent être remis au client par le prestataire sous un délai convenu entre les Parties. Si la demande est émise dans le cadre d'investigation déclenchée par un incident de sécurité, le prestataire travaillera en bonne intelligence avec un niveau de priorité adapté à la mesure de l'urgence de la situation générée par l'incident. | F30: C, D, E, F, H | G30: =IF(AND('1 - General description'!$G$51=FALSE, K30= TRUE),"Applicable","N.A") -> Applicable | K30: =OR(ISNUMBER(FIND('1 - General description'!$H$51,F30)),ISNUMBER(FIND('1 - General description'!$H$52,F30)),ISNUMBER(FIND('1 - General description'!$H$53,F30)),ISNUMBER(FIND('1 - General description'!$H$54,F30)),ISNUMBER(FIND('1 - General description'!$H$55,F30)),ISNUMBER(FIND('1 - General description'!$H$56,F30)),ISNUMBER(FIND('1 - General description'!$H$57,F30)),ISNUMBER(FIND('1 - General description'!$H$58,F30)),ISNUMBER(FIND('1 - General description'!$H$59,F30)),ISNUMBER(FIND('1 - General description'!$H$60,F30)),ISNUMBER(FIND('1 - General description'!$H$61,F30)),ISNUMBER(FIND('1 - General description'!$H$62,F30)),ISNUMBER(FIND('1 - General description'!$H$63,F30)),ISNUMBER(FIND('1 - General description'!$H$64,F30))) -> TRUE
A31: 5 | B31: Traceability / Traçabilité | C31: 5.6 | D31: Confidentiality of logs / Confidentialité des traces | E31: The parts of the logs which refer to the client are confidential and shall never be disclosed to another client. / Les parties des journaux qui concernent le client sont confidentielles et ne doivent en aucun cas être divulguées à un autre client. | F31: C, D, E, F, H | G31: =IF(AND('1 - General description'!$G$51=FALSE, K31= TRUE),"Applicable","N.A") -> Applicable | K31: =OR(ISNUMBER(FIND('1 - General description'!$H$51,F31)),ISNUMBER(FIND('1 - General description'!$H$52,F31)),ISNUMBER(FIND('1 - General description'!$H$53,F31)),ISNUMBER(FIND('1 - General description'!$H$54,F31)),ISNUMBER(FIND('1 - General description'!$H$55,F31)),ISNUMBER(FIND('1 - General description'!$H$56,F31)),ISNUMBER(FIND('1 - General description'!$H$57,F31)),ISNUMBER(FIND('1 - General description'!$H$58,F31)),ISNUMBER(FIND('1 - General description'!$H$59,F31)),ISNUMBER(FIND('1 - General description'!$H$60,F31)),ISNUMBER(FIND('1 - General description'!$H$61,F31)),ISNUMBER(FIND('1 - General description'!$H$62,F31)),ISNUMBER(FIND('1 - General description'!$H$63,F31)),ISNUMBER(FIND('1 - General description'!$H$64,F31))) -> TRUE
A32: 5 | B32: Traceability / Traçabilité | C32: 5.7 | D32: Integrity of logs / Intégrité des traces | E32: The service provider guarantees that all information in the logs can be acceptable according to the state of art (reliable timestamp, logs saved, etc.). / Le prestataire certifie que toutes les informations présentes sur les traces sont exploitables au regard de l’état de l’art (horodatage fiable, traces sauvegardées, etc.). | F32: C, D, E, F, H | G32: =IF(AND('1 - General description'!$G$51=FALSE, K32= TRUE),"Applicable","N.A") -> Applicable | K32: =OR(ISNUMBER(FIND('1 - General description'!$H$51,F32)),ISNUMBER(FIND('1 - General description'!$H$52,F32)),ISNUMBER(FIND('1 - General description'!$H$53,F32)),ISNUMBER(FIND('1 - General description'!$H$54,F32)),ISNUMBER(FIND('1 - General description'!$H$55,F32)),ISNUMBER(FIND('1 - General description'!$H$56,F32)),ISNUMBER(FIND('1 - General description'!$H$57,F32)),ISNUMBER(FIND('1 - General description'!$H$58,F32)),ISNUMBER(FIND('1 - General description'!$H$59,F32)),ISNUMBER(FIND('1 - General description'!$H$60,F32)),ISNUMBER(FIND('1 - General description'!$H$61,F32)),ISNUMBER(FIND('1 - General description'!$H$62,F32)),ISNUMBER(FIND('1 - General description'!$H$63,F32)),ISNUMBER(FIND('1 - General description'!$H$64,F32))) -> TRUE
A33: 6 | B33: Data protection / Protection des données | C33: 6.1 | D33: Use of data / Exploitation des données | E33: The service provider shall implement technical and organisational measures to prevent extraction of data by its staff (e.g. export of a copy of the database from a workstation used for administrative tasks). / Le prestataire met en œuvre des mesures techniques et organisationnelles pour empêcher des extractions d’information par des personnels (ex. extraction d’une copie de la base de données à partir d’un poste utilisé par ses personnels pour des tâches d'administration). | F33: I, J, Z | G33: =IF(K33= TRUE,"Applicable","N.A") -> Applicable | K33: =OR(ISNUMBER(FIND('1 - General description'!$H$51,F33)),ISNUMBER(FIND('1 - General description'!$H$52,F33)),ISNUMBER(FIND('1 - General description'!$H$53,F33)),ISNUMBER(FIND('1 - General description'!$H$54,F33)),ISNUMBER(FIND('1 - General description'!$H$55,F33)),ISNUMBER(FIND('1 - General description'!$H$56,F33)),ISNUMBER(FIND('1 - General description'!$H$57,F33)),ISNUMBER(FIND('1 - General description'!$H$58,F33)),ISNUMBER(FIND('1 - General description'!$H$59,F33)),ISNUMBER(FIND('1 - General description'!$H$60,F33)),ISNUMBER(FIND('1 - General description'!$H$61,F33)),ISNUMBER(FIND('1 - General description'!$H$62,F33)),ISNUMBER(FIND('1 - General description'!$H$63,F33)),ISNUMBER(FIND('1 - General description'!$H$64,F33))) -> TRUE
A34: 6 | B34: Data protection / Protection des données | C34: 6.2 | D34: Encryption / Chiffrement | E34: The service provider must protect the confidentiality and integrity of the data by encrypting all communications flows with encryption algorithms and protocols that meet current and non-obsolete security standards (eg replacement of SSL by TLS). Unencrypted communication flow (FTP, HTTP, etc.) are not allowed. The service provider must protect the encryption keys (e.g. use of a safe) / Le prestataire doit protéger la confidentialité et l’intégrité des données en chiffrant tous les flux avec les algorithmes et protocoles de chiffrement répondants aux standards sécurités actuels et non obsolètes (ex. remplacement de SSL par TLS). Les flux non chiffrés (FTP, HTTP, etc.) ne sont pas autorisés. Le prestataire doit protéger les clés de chiffrement (ex. utilisation d'un coffre fort) | F34: I, J | G34: =IF(AND('1 - General description'!$G$51=FALSE, K34= TRUE),"Applicable","N.A") -> Applicable | K34: =OR(ISNUMBER(FIND('1 - General description'!$H$51,F34)),ISNUMBER(FIND('1 - General description'!$H$52,F34)),ISNUMBER(FIND('1 - General description'!$H$53,F34)),ISNUMBER(FIND('1 - General description'!$H$54,F34)),ISNUMBER(FIND('1 - General description'!$H$55,F34)),ISNUMBER(FIND('1 - General description'!$H$56,F34)),ISNUMBER(FIND('1 - General description'!$H$57,F34)),ISNUMBER(FIND('1 - General description'!$H$58,F34)),ISNUMBER(FIND('1 - General description'!$H$59,F34)),ISNUMBER(FIND('1 - General description'!$H$60,F34)),ISNUMBER(FIND('1 - General description'!$H$61,F34)),ISNUMBER(FIND('1 - General description'!$H$62,F34)),ISNUMBER(FIND('1 - General description'!$H$63,F34)),ISNUMBER(FIND('1 - General description'!$H$64,F34))) -> TRUE
A35: 6 | B35: Data protection / Protection des données | C35: 6.3 | D35: Production data / Données de production | E35: The service provider shall establish procedures to ensure that no production data is replicated in non-production environments and that only fictitious data is used for test and acceptance purposes, unless the client has explicitly specified otherwise and validated in writing. / Le prestataire met en place des procédures pour s’assurer que des données de production ne soient pas répliquées dans des environnements hors production et que seules des données fictives ou anonymisées soient utilisées à des fins de test et de recette, sauf si le client a donné par écrit et préalablement un avis contraire. | F35: I, J | G35: =IF(AND('1 - General description'!$G$51=FALSE, K35= TRUE),"Applicable","N.A") -> Applicable | K35: =OR(ISNUMBER(FIND('1 - General description'!$H$51,F35)),ISNUMBER(FIND('1 - General description'!$H$52,F35)),ISNUMBER(FIND('1 - General description'!$H$53,F35)),ISNUMBER(FIND('1 - General description'!$H$54,F35)),ISNUMBER(FIND('1 - General description'!$H$55,F35)),ISNUMBER(FIND('1 - General description'!$H$56,F35)),ISNUMBER(FIND('1 - General description'!$H$57,F35)),ISNUMBER(FIND('1 - General description'!$H$58,F35)),ISNUMBER(FIND('1 - General description'!$H$59,F35)),ISNUMBER(FIND('1 - General description'!$H$60,F35)),ISNUMBER(FIND('1 - General description'!$H$61,F35)),ISNUMBER(FIND('1 - General description'!$H$62,F35)),ISNUMBER(FIND('1 - General description'!$H$63,F35)),ISNUMBER(FIND('1 - General description'!$H$64,F35))) -> TRUE
A36: 6 | B36: Data protection / Protection des données | C36: 6.4 | D36: Data backup / Sauvegarde | E36: Based on the requirements regarding the availability and integrity of data, the service provider shall implement, supervise and regularly test a replication and backup system for the data it hosts. The backup plan (frequency, type, scope, retention, test...) is described in a documentation and must be provided to the client on demand. / Le prestataire met en œuvre, supervise et teste régulièrement un dispositif de réplication et de sauvegarde des données qu'elle héberge. Le Plan de sauvegarde (fréquence, nature, périmètre, rétention, test...) est documenté et doit être fourni au Client sur demande. | F36: D, E, F, H | G36: =IF(AND('1 - General description'!$G$51=FALSE, K36= TRUE),"Applicable","N.A") -> Applicable | K36: =OR(ISNUMBER(FIND('1 - General description'!$H$51,F36)),ISNUMBER(FIND('1 - General description'!$H$52,F36)),ISNUMBER(FIND('1 - General description'!$H$53,F36)),ISNUMBER(FIND('1 - General description'!$H$54,F36)),ISNUMBER(FIND('1 - General description'!$H$55,F36)),ISNUMBER(FIND('1 - General description'!$H$56,F36)),ISNUMBER(FIND('1 - General description'!$H$57,F36)),ISNUMBER(FIND('1 - General description'!$H$58,F36)),ISNUMBER(FIND('1 - General description'!$H$59,F36)),ISNUMBER(FIND('1 - General description'!$H$60,F36)),ISNUMBER(FIND('1 - General description'!$H$61,F36)),ISNUMBER(FIND('1 - General description'!$H$62,F36)),ISNUMBER(FIND('1 - General description'!$H$63,F36)),ISNUMBER(FIND('1 - General description'!$H$64,F36))) -> TRUE
A37: 6 | B37: Data protection / Protection des données | C37: 6.5 | D37: Disposal / Mise au rebut | E37: Disposal of equipment used for data storage shall be subject to a prior destruction of data using deletion tools which prevent the recovery of data by a third party. / La mise au rebut de matériels assurant le stockage de données doit faire l’objet d’une destruction préalable des données à l’aide d’outils d’effacement empêchant la récupération des données par un tiers. | F37: I, J | G37: =IF(AND('1 - General description'!$G$51=FALSE, K37= TRUE),"Applicable","N.A") -> Applicable | K37: =OR(ISNUMBER(FIND('1 - General description'!$H$51,F37)),ISNUMBER(FIND('1 - General description'!$H$52,F37)),ISNUMBER(FIND('1 - General description'!$H$53,F37)),ISNUMBER(FIND('1 - General description'!$H$54,F37)),ISNUMBER(FIND('1 - General description'!$H$55,F37)),ISNUMBER(FIND('1 - General description'!$H$56,F37)),ISNUMBER(FIND('1 - General description'!$H$57,F37)),ISNUMBER(FIND('1 - General description'!$H$58,F37)),ISNUMBER(FIND('1 - General description'!$H$59,F37)),ISNUMBER(FIND('1 - General description'!$H$60,F37)),ISNUMBER(FIND('1 - General description'!$H$61,F37)),ISNUMBER(FIND('1 - General description'!$H$62,F37)),ISNUMBER(FIND('1 - General description'!$H$63,F37)),ISNUMBER(FIND('1 - General description'!$H$64,F37))) -> TRUE
A38: 6 | B38: Data protection / Protection des données | C38: 6.6 | D38: Information security exchange / Sécurité des échanges | E38: It is recommended not to exchange confiential information by mail. Should such exchanges occur, attachments containing sensitive data must be encrypted and the key sent via another channel of communication (orally, for instance). It is nevertheless preferable to use exchange file solutions other than mail for sensitive data. It is forbidden to use public solutions, such as WeTransfer, SwissTranser, Google Drive, etc. / Il est recommandé de ne pas transmettre d'informations confidentielles par mail. Si de tels échanges ont lieu, les pièce-jointes contenant des données sensibles doivent être chiffrées et les mots de passe / clés de chiffrement doivent être transmis via un autre canal de communication que le mail (ex. SMS). Il est préférable d'utiliser des solutions d'échanges de fichiers autre que les mails pour ce qui concerne les données sensibles. Il est interdit d'utiliser des solutions publiques tels que WeTransfer, SwissTransfer, Google Drive, etc. | F38: I, Z | G38: =IF(K38= TRUE,"Applicable","N.A") -> Applicable | K38: =OR(ISNUMBER(FIND('1 - General description'!$H$51,F38)),ISNUMBER(FIND('1 - General description'!$H$52,F38)),ISNUMBER(FIND('1 - General description'!$H$53,F38)),ISNUMBER(FIND('1 - General description'!$H$54,F38)),ISNUMBER(FIND('1 - General description'!$H$55,F38)),ISNUMBER(FIND('1 - General description'!$H$56,F38)),ISNUMBER(FIND('1 - General description'!$H$57,F38)),ISNUMBER(FIND('1 - General description'!$H$58,F38)),ISNUMBER(FIND('1 - General description'!$H$59,F38)),ISNUMBER(FIND('1 - General description'!$H$60,F38)),ISNUMBER(FIND('1 - General description'!$H$61,F38)),ISNUMBER(FIND('1 - General description'!$H$62,F38)),ISNUMBER(FIND('1 - General description'!$H$63,F38)),ISNUMBER(FIND('1 - General description'!$H$64,F38))) -> TRUE
A39: 6 | B39: Data protection / Protection des données | C39: 6.7 | D39: Storage / Stockage | E39: For service delivery requiring storage, the client and the service provider shall agree on a secure storage solution. The service provider shall ensure that the solution, whether or not it is the owner of that solution, is not vulnerable, that it has no open ports which might constitute a security flaw and that access is protected using strong passwords. / Dans le cadre de missions nécessitant des zones de stockage, le client et le prestataire conviennent d’une solution de stockage sécurisée. Le prestataire veille à ce que cette solution, qu'elle en soit propriétaire ou non, ne soit pas vulnérable, qu’elle ne comporte pas de ports ouverts pouvant constituer une faille de sécurité et que les accès à cette solution soient protégés par des mots de passe robustes. | F39: I, J, Z | G39: =IF(K39= TRUE,"Applicable","N.A") -> Applicable | K39: =OR(ISNUMBER(FIND('1 - General description'!$H$51,F39)),ISNUMBER(FIND('1 - General description'!$H$52,F39)),ISNUMBER(FIND('1 - General description'!$H$53,F39)),ISNUMBER(FIND('1 - General description'!$H$54,F39)),ISNUMBER(FIND('1 - General description'!$H$55,F39)),ISNUMBER(FIND('1 - General description'!$H$56,F39)),ISNUMBER(FIND('1 - General description'!$H$57,F39)),ISNUMBER(FIND('1 - General description'!$H$58,F39)),ISNUMBER(FIND('1 - General description'!$H$59,F39)),ISNUMBER(FIND('1 - General description'!$H$60,F39)),ISNUMBER(FIND('1 - General description'!$H$61,F39)),ISNUMBER(FIND('1 - General description'!$H$62,F39)),ISNUMBER(FIND('1 - General description'!$H$63,F39)),ISNUMBER(FIND('1 - General description'!$H$64,F39))) -> TRUE
A40: 6 | B40: Data protection / Protection des données | C40: 6.8 | D40: Regulatory compliance / Conformité réglementaire | E40: The service provider shall ensure protection of the personal data that it hosts or might access when delivering the service. In particular, it undertakes to comply with regulations about the processing of personal data. / Le prestataire assure la protection des données à caractère personnel qu’elle héberge ou auxquelles elle peut accéder dans le cadre de sa mission. Notamment elle s’engage à respecter la réglementation applicable en matière de protection des données personnelles. | F40: J | G40: =IF(AND('1 - General description'!$G$51=FALSE, K40= TRUE),"Applicable","N.A") -> N.A | K40: =OR(ISNUMBER(FIND('1 - General description'!$H$51,F40)),ISNUMBER(FIND('1 - General description'!$H$52,F40)),ISNUMBER(FIND('1 - General description'!$H$53,F40)),ISNUMBER(FIND('1 - General description'!$H$54,F40)),ISNUMBER(FIND('1 - General description'!$H$55,F40)),ISNUMBER(FIND('1 - General description'!$H$56,F40)),ISNUMBER(FIND('1 - General description'!$H$57,F40)),ISNUMBER(FIND('1 - General description'!$H$58,F40)),ISNUMBER(FIND('1 - General description'!$H$59,F40)),ISNUMBER(FIND('1 - General description'!$H$60,F40)),ISNUMBER(FIND('1 - General description'!$H$61,F40)),ISNUMBER(FIND('1 - General description'!$H$62,F40)),ISNUMBER(FIND('1 - General description'!$H$63,F40)),ISNUMBER(FIND('1 - General description'!$H$64,F40))) -> FALSE
A41: 6 | B41: Data protection / Protection des données | C41: 6.9 | D41: Data Retention and Right to Erasure / Purge des données et droit à l’oubli | E41: The service provider implements a mechanism to delete personal data of customers beyond a default retention period of 28 days. In case of specific needs or regulatory requirements, different storage arrangements may be put in place, provided they are agreed with the customer. The service provider also undertakes to apply the customer’s procedures regarding the right to be forgotten and the erasure of data. It ensures that deleted data is permanently erased from all active systems, backups and logs in accordance with the agreed terms. / Le prestataire met en œuvre un mécanisme de suppression des données personnelles des clients au-delà d’une durée maximale de conservation par défaut de 28 jours. En cas de besoins spécifiques ou d’exigences réglementaires, des modalités de conservation différentes peuvent être mises en place, à condition qu’elles soient définies avec le client. Le prestataire s’engage par ailleurs à appliquer les procédures du client en matière de droit à l’oubli et d’effacement des données. Il garantit que les données supprimées sont définitivement effacées de l’ensemble des systèmes actifs, des sauvegardes et des journaux, conformément aux modalités convenues. | F41: J | G41: =IF(AND('1 - General description'!$G$51=FALSE, K41= TRUE),"Applicable","N.A") -> N.A | K41: =AND(OR(ISNUMBER(FIND('1 - General description'!$H$51,F41)),ISNUMBER(FIND('1 - General description'!$H$52,F41)),ISNUMBER(FIND('1 - General description'!$H$53,F41)),ISNUMBER(FIND('1 - General description'!$H$54,F41)),ISNUMBER(FIND('1 - General description'!$H$55,F41)),ISNUMBER(FIND('1 - General description'!$H$56,F41)),ISNUMBER(FIND('1 - General description'!$H$57,F41)),ISNUMBER(FIND('1 - General description'!$H$58,F41)),ISNUMBER(FIND('1 - General description'!$H$59,F41)),ISNUMBER(FIND('1 - General description'!$H$60,F41)),ISNUMBER(FIND('1 - General description'!$H$61,F41)),ISNUMBER(FIND('1 - General description'!$H$62,F41)),ISNUMBER(FIND('1 - General description'!$H$63,F41)),ISNUMBER(FIND('1 - General description'!$H$64,F41))), IF('2 - Qualification'!C12="Yes","Yes","No")) -> FALSE
A42: 7 | B42: Infrastructure security / Sécurité de l'infrastructure | C42: 7.1 | D42: Documentation | E42: The service provider shall ensure an up-to-date documentation and inventory of assets for which it is responsible on behalf of the client or the platforms it makes available to the client within the context of the contract. / Le prestataire doit assurer une mise à jour des documentations et des inventaires des ressources concernant les composants qu’elle prend en charge pour le compte du client ou des plates-formes qu’elle met à disposition du client dans le cadre de la prestation. | F42: D, E, F, H | G42: =IF(AND('1 - General description'!$G$51=FALSE, K42= TRUE),"Applicable","N.A") -> Applicable | K42: =OR(ISNUMBER(FIND('1 - General description'!$H$51,F42)),ISNUMBER(FIND('1 - General description'!$H$52,F42)),ISNUMBER(FIND('1 - General description'!$H$53,F42)),ISNUMBER(FIND('1 - General description'!$H$54,F42)),ISNUMBER(FIND('1 - General description'!$H$55,F42)),ISNUMBER(FIND('1 - General description'!$H$56,F42)),ISNUMBER(FIND('1 - General description'!$H$57,F42)),ISNUMBER(FIND('1 - General description'!$H$58,F42)),ISNUMBER(FIND('1 - General description'!$H$59,F42)),ISNUMBER(FIND('1 - General description'!$H$60,F42)),ISNUMBER(FIND('1 - General description'!$H$61,F42)),ISNUMBER(FIND('1 - General description'!$H$62,F42)),ISNUMBER(FIND('1 - General description'!$H$63,F42)),ISNUMBER(FIND('1 - General description'!$H$64,F42))) -> TRUE
A43: 7 | B43: Infrastructure security / Sécurité de l'infrastructure | C43: 7.2 | D43: Networks / Réseaux | E43: All flows must be encrypted using reliable protocols (SSH, TLS, IPsec, etc.) which guarantee the confidentiality and integrity of data. This is particularly important for any flow transiting over a public network. / Tous les flux doivent être chiffrés par des procédés fiables (SSH, TLS, IPsec, etc.), garantissant la confidentialité et l’intégrité des données. Cela est particulièrement important pour tous les flux circulant sur un réseau public. | F43: M | G43: =IF(AND('1 - General description'!$G$51=FALSE, K43= TRUE),"Applicable","N.A") -> Applicable | K43: =OR(ISNUMBER(FIND('1 - General description'!$H$51,F43)),ISNUMBER(FIND('1 - General description'!$H$52,F43)),ISNUMBER(FIND('1 - General description'!$H$53,F43)),ISNUMBER(FIND('1 - General description'!$H$54,F43)),ISNUMBER(FIND('1 - General description'!$H$55,F43)),ISNUMBER(FIND('1 - General description'!$H$56,F43)),ISNUMBER(FIND('1 - General description'!$H$57,F43)),ISNUMBER(FIND('1 - General description'!$H$58,F43)),ISNUMBER(FIND('1 - General description'!$H$59,F43)),ISNUMBER(FIND('1 - General description'!$H$60,F43)),ISNUMBER(FIND('1 - General description'!$H$61,F43)),ISNUMBER(FIND('1 - General description'!$H$62,F43)),ISNUMBER(FIND('1 - General description'!$H$63,F43)),ISNUMBER(FIND('1 - General description'!$H$64,F43))) -> TRUE
A44: 7 | B44: Infrastructure security / Sécurité de l'infrastructure | C44: 7.3 | D44: Interfaces and back office / Interfaces et backoffice | E44: Exchange of data between different components of the information system of the service provider and/or the client, shall reliable on secure mechanisms for transport (encryption protocol) and authentication. These mechanisms must be regularly updated. / La mise en œuvre d’échanges de données entre différents composants du système d'information du prestataire et/ou du client, doit s'appuyer sur des mécanismes sécurisés au niveau du transport (chiffrement des communications) et de l’authentification. Ces dispositifs doivent être maintenus à jour. | F44: C, D, E, F, H, M | G44: =IF(AND('1 - General description'!$G$51=FALSE, K44= TRUE),"Applicable","N.A") -> Applicable | K44: =OR(ISNUMBER(FIND('1 - General description'!$H$51,F44)),ISNUMBER(FIND('1 - General description'!$H$52,F44)),ISNUMBER(FIND('1 - General description'!$H$53,F44)),ISNUMBER(FIND('1 - General description'!$H$54,F44)),ISNUMBER(FIND('1 - General description'!$H$55,F44)),ISNUMBER(FIND('1 - General description'!$H$56,F44)),ISNUMBER(FIND('1 - General description'!$H$57,F44)),ISNUMBER(FIND('1 - General description'!$H$58,F44)),ISNUMBER(FIND('1 - General description'!$H$59,F44)),ISNUMBER(FIND('1 - General description'!$H$60,F44)),ISNUMBER(FIND('1 - General description'!$H$61,F44)),ISNUMBER(FIND('1 - General description'!$H$62,F44)),ISNUMBER(FIND('1 - General description'!$H$63,F44)),ISNUMBER(FIND('1 - General description'!$H$64,F44))) -> TRUE
A45: 7 | B45: Infrastructure security / Sécurité de l'infrastructure | C45: 7.4 | D45: Scope of access / Périmètre d'accès | E45: The service provider undertakes to access only to the systems required for the service delivery. / Le prestataire s’engage à n’accéder qu’aux systèmes nécessaires à l’exercice de sa mission. | F45: C, D, E, F, H, M | G45: =IF(AND('1 - General description'!$G$51=FALSE, K45= TRUE),"Applicable","N.A") -> Applicable | K45: =OR(ISNUMBER(FIND('1 - General description'!$H$51,F45)),ISNUMBER(FIND('1 - General description'!$H$52,F45)),ISNUMBER(FIND('1 - General description'!$H$53,F45)),ISNUMBER(FIND('1 - General description'!$H$54,F45)),ISNUMBER(FIND('1 - General description'!$H$55,F45)),ISNUMBER(FIND('1 - General description'!$H$56,F45)),ISNUMBER(FIND('1 - General description'!$H$57,F45)),ISNUMBER(FIND('1 - General description'!$H$58,F45)),ISNUMBER(FIND('1 - General description'!$H$59,F45)),ISNUMBER(FIND('1 - General description'!$H$60,F45)),ISNUMBER(FIND('1 - General description'!$H$61,F45)),ISNUMBER(FIND('1 - General description'!$H$62,F45)),ISNUMBER(FIND('1 - General description'!$H$63,F45)),ISNUMBER(FIND('1 - General description'!$H$64,F45))) -> TRUE
A46: 7 | B46: Infrastructure security / Sécurité de l'infrastructure | C46: 7.5 | D46: Connection on the client’s premises / Connexions sur le site du Client | E46: The service provider commits not to connect their workstations to the local network on the customer's premises. The use of internal network is strictly reserved to the devices provided by the customer. / Le prestataire s'engage à ne peut pas connecter au réseau ses matériels informatiques dans les locaux du client. L'utilisation du réseau interne du client est réservé au matériel fourni par celui-ci. | F46: C, D, H | G46: =IF(AND('1 - General description'!$G$51=FALSE, K46= TRUE),"Applicable","N.A") -> N.A | K46: =OR(ISNUMBER(FIND('1 - General description'!$H$51,F46)),ISNUMBER(FIND('1 - General description'!$H$52,F46)),ISNUMBER(FIND('1 - General description'!$H$53,F46)),ISNUMBER(FIND('1 - General description'!$H$54,F46)),ISNUMBER(FIND('1 - General description'!$H$55,F46)),ISNUMBER(FIND('1 - General description'!$H$56,F46)),ISNUMBER(FIND('1 - General description'!$H$57,F46)),ISNUMBER(FIND('1 - General description'!$H$58,F46)),ISNUMBER(FIND('1 - General description'!$H$59,F46)),ISNUMBER(FIND('1 - General description'!$H$60,F46)),ISNUMBER(FIND('1 - General description'!$H$61,F46)),ISNUMBER(FIND('1 - General description'!$H$62,F46)),ISNUMBER(FIND('1 - General description'!$H$63,F46)),ISNUMBER(FIND('1 - General description'!$H$64,F46))) -> FALSE
A47: 7 | B47: Infrastructure security / Sécurité de l'infrastructure | C47: 7.6 | D47: Guest connection / Connexion invité | E47: The service provider’s staff working on a short-term mission shall use, when available, guest Internet access provided by the client and dedicated to temporary third-party connections. They must undertake to comply with the guest charter governing this Internet access prior to establishing any connection to the Internet and shall comply with the security measures in place, such as proxies and URL filtering. / Les personnels du prestataire en mission de courte durée utiliseront, lorsqu’elles existent, des connexions à Internet de type Guest sur des réseaux du client, dédiés à des connexions occasionnelles de tiers. Ils devront valider la charte d’usage de ces réseaux préalablement à toute connexion sur Internet et respecter les dispositifs de sécurité mis en place tels que des proxys et filtres d’URL par exemple. | F47: K | G47: =IF(AND('1 - General description'!$G$51=FALSE, K47= TRUE),"Applicable","N.A") -> N.A | K47: =OR(ISNUMBER(FIND('1 - General description'!$H$51,F47)),ISNUMBER(FIND('1 - General description'!$H$52,F47)),ISNUMBER(FIND('1 - General description'!$H$53,F47)),ISNUMBER(FIND('1 - General description'!$H$54,F47)),ISNUMBER(FIND('1 - General description'!$H$55,F47)),ISNUMBER(FIND('1 - General description'!$H$56,F47)),ISNUMBER(FIND('1 - General description'!$H$57,F47)),ISNUMBER(FIND('1 - General description'!$H$58,F47)),ISNUMBER(FIND('1 - General description'!$H$59,F47)),ISNUMBER(FIND('1 - General description'!$H$60,F47)),ISNUMBER(FIND('1 - General description'!$H$61,F47)),ISNUMBER(FIND('1 - General description'!$H$62,F47)),ISNUMBER(FIND('1 - General description'!$H$63,F47)),ISNUMBER(FIND('1 - General description'!$H$64,F47))) -> FALSE
A48: 7 | B48: Infrastructure security / Sécurité de l'infrastructure | C48: 7.7 | D48: Workstations and mobility / Poste de travail et mobilité | E48: The service provider undertakes to secure the fixed and mobile workstations used by its own staff and the staff of its subcontractors for the provision of the services in order to ensure that such devices do not give rise to any security flaws. Access to the client’s data using mobile devices must be strictly controlled, whether such devices are owned by the service provider, its subcontractors or its/their employees. The storage of data belonging to the client on such devices – even temporarily – shall be subject to the prior consent of the client. The devices must be protected against intrusion or the disclosure of information in the event of theft. / Le prestataire s’engage à sécuriser les postes de travail fixes et mobiles utilisés par ses personnels et ceux de ses sous-traitants pour l’exécution des prestations, afin que ces matériels ne soient pas à l’origine d’une faille de sécurité. L’accès à des données du client à travers un matériel mobile doit être strictement contrôlé, que ce matériel soit la propriété du prestataire ou de ses sous-traitants ou bien qu’il soit la propriété de ses/leurs personnels. Le stockage de données appartenant au client sur ces matériels, même temporaire, doit faire l'objet d'un accord écrit et préalable du client. Ces matériels doivent être protégés contre les intrusions logiques ou la divulgation d’informations en cas de vol. | F48: A, B, C, D, E, F, G, H | G48: =IF(AND('1 - General description'!$G$51=FALSE, K48= TRUE),"Applicable","N.A") -> Applicable | K48: =OR(ISNUMBER(FIND('1 - General description'!$H$51,F48)),ISNUMBER(FIND('1 - General description'!$H$52,F48)),ISNUMBER(FIND('1 - General description'!$H$53,F48)),ISNUMBER(FIND('1 - General description'!$H$54,F48)),ISNUMBER(FIND('1 - General description'!$H$55,F48)),ISNUMBER(FIND('1 - General description'!$H$56,F48)),ISNUMBER(FIND('1 - General description'!$H$57,F48)),ISNUMBER(FIND('1 - General description'!$H$58,F48)),ISNUMBER(FIND('1 - General description'!$H$59,F48)),ISNUMBER(FIND('1 - General description'!$H$60,F48)),ISNUMBER(FIND('1 - General description'!$H$61,F48)),ISNUMBER(FIND('1 - General description'!$H$62,F48)),ISNUMBER(FIND('1 - General description'!$H$63,F48)),ISNUMBER(FIND('1 - General description'!$H$64,F48))) -> TRUE
A49: 7 | B49: Infrastructure security / Sécurité de l'infrastructure | C49: 7.8 | D49: DMARC Policy Compliance / Conformité à la politique DMARC | E49: The service provider guarantees that the DMARC and SPF configurations of domains and sub-domains used for the services provided and likely to send emails comply with the client's security requirements. The DMARC policy must contains the value "p=reject", and the SPF value must be "v=spf1 -al". The service provider must also ensure that the associated DNS records are correctly published and kept up to date. / Le prestataire garantit que les configurations DMARC et SPF des domaines ou sous-domaines utilisés dans le cadre du service et susceptible d'envoyer des e-mails sont conformes aux exigences de sécurité du client. La configuration DMARC doit contenir la valeur "p=reject", et la valeur du SPF doit être "v=spf1 -all". Le partenaire doit également s’assurer que les enregistrements DNS associés sont correctement publiés et maintenus à jour. | F49: E,F,G | G49: =IF(AND('1 - General description'!$G$51=FALSE, K49= TRUE),"Applicable","N.A") -> Applicable | K49: =OR(ISNUMBER(FIND('1 - General description'!$H$51,F49)),ISNUMBER(FIND('1 - General description'!$H$52,F49)),ISNUMBER(FIND('1 - General description'!$H$53,F49)),ISNUMBER(FIND('1 - General description'!$H$54,F49)),ISNUMBER(FIND('1 - General description'!$H$55,F49)),ISNUMBER(FIND('1 - General description'!$H$56,F49)),ISNUMBER(FIND('1 - General description'!$H$57,F49)),ISNUMBER(FIND('1 - General description'!$H$58,F49)),ISNUMBER(FIND('1 - General description'!$H$59,F49)),ISNUMBER(FIND('1 - General description'!$H$60,F49)),ISNUMBER(FIND('1 - General description'!$H$61,F49)),ISNUMBER(FIND('1 - General description'!$H$62,F49)),ISNUMBER(FIND('1 - General description'!$H$63,F49)),ISNUMBER(FIND('1 - General description'!$H$64,F49))) -> TRUE
A50: 7 | B50: Infrastructure security / Sécurité de l'infrastructure | C50: 7.9 | D50: Web Application Firewall (WAF) Availability / Présence d’un pare-feu applicatif (WAF) | E50: The service provider must have a Web Application Firewall (WAF) protecting all services exposed to the Internet. This WAF must comply with the security requirements defined by the client. If the service provider does not have a WAF, or if the existing measures do not meet the client’s requirements, the client may require the use of its own WAF to protect the relevant services. The service provider shall then cooperate in its implementation, ensuring the compatibility of its systems. Any modification to the WAF configuration must be communicated to the client and approved by them. / Le prestataire doit disposer d’un pare-feu applicatif (WAF) protégeant l’ensemble des services exposés sur Internet. Ce WAF doit être conforme aux exigences de sécurité définies par le client. Si le prestataire ne dispose pas de WAF ou si les mesures en place ne répondent pas aux exigences du client, ce dernier pourra imposer l’usage de son propre WAF en protection des services concernés. Le prestataire devra alors coopérer à sa mise en œuvre, en assurant la compatibilité de ses systèmes. Toute modification de configuration du WAF devra être communiquées au client et validées par celui-ci. | F50: E,F,G | G50: =IF(AND('1 - General description'!$G$51=FALSE, K50= TRUE),"Applicable","N.A") -> Applicable | K50: =OR(ISNUMBER(FIND('1 - General description'!$H$51,F50)),ISNUMBER(FIND('1 - General description'!$H$52,F50)),ISNUMBER(FIND('1 - General description'!$H$53,F50)),ISNUMBER(FIND('1 - General description'!$H$54,F50)),ISNUMBER(FIND('1 - General description'!$H$55,F50)),ISNUMBER(FIND('1 - General description'!$H$56,F50)),ISNUMBER(FIND('1 - General description'!$H$57,F50)),ISNUMBER(FIND('1 - General description'!$H$58,F50)),ISNUMBER(FIND('1 - General description'!$H$59,F50)),ISNUMBER(FIND('1 - General description'!$H$60,F50)),ISNUMBER(FIND('1 - General description'!$H$61,F50)),ISNUMBER(FIND('1 - General description'!$H$62,F50)),ISNUMBER(FIND('1 - General description'!$H$63,F50)),ISNUMBER(FIND('1 - General description'!$H$64,F50))) -> TRUE
A51: 8 | B51: Hosting / Hébergement | C51: 8.1 | D51: Territoriality / Territorialité | E51: Based on the risk analysis conducted by the client, the contract may require that those sites be located in a specific region. In particular, the hosting of its data or of the staff accessing that data must be within the European Union. / Les données ou les personnels accédant à des données personnelles de personnes issues de l'Union Européenne doivent être localisées sur le sol de l'Union Européenne. | F51: I, J | G51: =IF(AND('1 - General description'!$G$51=FALSE, K51= TRUE),"Applicable","N.A") -> Applicable | K51: =OR(ISNUMBER(FIND('1 - General description'!$H$51,F51)),ISNUMBER(FIND('1 - General description'!$H$52,F51)),ISNUMBER(FIND('1 - General description'!$H$53,F51)),ISNUMBER(FIND('1 - General description'!$H$54,F51)),ISNUMBER(FIND('1 - General description'!$H$55,F51)),ISNUMBER(FIND('1 - General description'!$H$56,F51)),ISNUMBER(FIND('1 - General description'!$H$57,F51)),ISNUMBER(FIND('1 - General description'!$H$58,F51)),ISNUMBER(FIND('1 - General description'!$H$59,F51)),ISNUMBER(FIND('1 - General description'!$H$60,F51)),ISNUMBER(FIND('1 - General description'!$H$61,F51)),ISNUMBER(FIND('1 - General description'!$H$62,F51)),ISNUMBER(FIND('1 - General description'!$H$63,F51)),ISNUMBER(FIND('1 - General description'!$H$64,F51))) -> TRUE
A52: 8 | B52: Hosting / Hébergement | C52: 8.2 | D52: Physical and environmental security / Sécurité physique et environnementale | E52: The service provider must ensure the security of hosting sites both in terms of physical access to the premises (24/7 surveillance, anti-intrusion systems, control and recording of access by security guards, airlock doors and means of identification, physical protection of equipment, locking of doors and windows, etc.) and in terms of environmental security (telecommunications, electrical protection and backup power, air conditioning, protection against fire, lightning and water damage, detectors and alarms). The service provider shall make a description of these measures available to the client. / Le prestataire doit assurer la sécurité des lieux d’hébergement sur le plan de l’accès physique aux locaux (surveillance des locaux 24/7, dispositifs anti-intrusion, contrôle et enregistrement des accès par gardiennage, sas et moyen d'identification, protection physique des équipements, verrouillage des baies, etc.) et de la sécurité environnementale (télécommunications, protection et redondances électriques, climatisation, protection contre l’incendie, la foudre et les dégâts des eaux, détecteurs et alarmes). le prestataire tient à disposition du client une description de ces dispositifs. | F52: C, D, E, F | G52: =IF(AND('1 - General description'!$G$51=FALSE, K52= TRUE),"Applicable","N.A") -> Applicable | K52: =OR(ISNUMBER(FIND('1 - General description'!$H$51,F52)),ISNUMBER(FIND('1 - General description'!$H$52,F52)),ISNUMBER(FIND('1 - General description'!$H$53,F52)),ISNUMBER(FIND('1 - General description'!$H$54,F52)),ISNUMBER(FIND('1 - General description'!$H$55,F52)),ISNUMBER(FIND('1 - General description'!$H$56,F52)),ISNUMBER(FIND('1 - General description'!$H$57,F52)),ISNUMBER(FIND('1 - General description'!$H$58,F52)),ISNUMBER(FIND('1 - General description'!$H$59,F52)),ISNUMBER(FIND('1 - General description'!$H$60,F52)),ISNUMBER(FIND('1 - General description'!$H$61,F52)),ISNUMBER(FIND('1 - General description'!$H$62,F52)),ISNUMBER(FIND('1 - General description'!$H$63,F52)),ISNUMBER(FIND('1 - General description'!$H$64,F52))) -> TRUE
A53: 8 | B53: Hosting / Hébergement | C53: 8.3 | D53: Security of hosted systems / Sécurité des systèmes hébergés | E53: The service provider shall ensure network partitioning and the integrity of the servers and workstations that it hosts through the application of patches, system hardening, malware protection, and intrusion detection and prevention tools, etc. / Le prestataire assure le cloisonnement des réseaux et l’intégrité des serveurs et postes de travail qu'elle héberge : application des correctifs, durcissement système, lutte contre les logiciels malveillants, outils de détection et de protection contre les intrusions, etc. | F53: C, D, E, F | G53: =IF(AND('1 - General description'!$G$51=FALSE, K53= TRUE),"Applicable","N.A") -> Applicable | K53: =OR(ISNUMBER(FIND('1 - General description'!$H$51,F53)),ISNUMBER(FIND('1 - General description'!$H$52,F53)),ISNUMBER(FIND('1 - General description'!$H$53,F53)),ISNUMBER(FIND('1 - General description'!$H$54,F53)),ISNUMBER(FIND('1 - General description'!$H$55,F53)),ISNUMBER(FIND('1 - General description'!$H$56,F53)),ISNUMBER(FIND('1 - General description'!$H$57,F53)),ISNUMBER(FIND('1 - General description'!$H$58,F53)),ISNUMBER(FIND('1 - General description'!$H$59,F53)),ISNUMBER(FIND('1 - General description'!$H$60,F53)),ISNUMBER(FIND('1 - General description'!$H$61,F53)),ISNUMBER(FIND('1 - General description'!$H$62,F53)),ISNUMBER(FIND('1 - General description'!$H$63,F53)),ISNUMBER(FIND('1 - General description'!$H$64,F53))) -> TRUE
... A56: 9 | B56: Resilience and level of service / Continuité et niveau de service | C56: 9.1 | D56: Business Continuity Plan and Disaster Recovery Plan / Plan de continuité et de reprise d'activité | E56: The service provider shall implement measures to ensure continuity and shall implement Disaster Recovery Plan compliant with contractual clauses. The service provider tests this DRP periodically. At the request of the client, and at agreed dates, the client will particpate to the testing of the Plan in order to measure service performance. / Le prestataire met en œuvre des dispositifs assurant la continuité d'activité et élabore un Plan de Reprise d'Activité conformément aux exigences contractuelles. Il procède régulièrement à des tests de ce Plan. A la demande du client et à des dates convenues entre les Parties, le prestataire participera au test du Plan par le client, au titre de la mesure de la performance du service. | F56: C, D, E, F, H | G56: =IF(AND('1 - General description'!$G$51=FALSE, K56= TRUE),"Applicable","N.A") -> Applicable | K56: =OR(ISNUMBER(FIND('1 - General description'!$H$51,F56)),ISNUMBER(FIND('1 - General description'!$H$52,F56)),ISNUMBER(FIND('1 - General description'!$H$53,F56)),ISNUMBER(FIND('1 - General description'!$H$54,F56)),ISNUMBER(FIND('1 - General description'!$H$55,F56)),ISNUMBER(FIND('1 - General description'!$H$56,F56)),ISNUMBER(FIND('1 - General description'!$H$57,F56)),ISNUMBER(FIND('1 - General description'!$H$58,F56)),ISNUMBER(FIND('1 - General description'!$H$59,F56)),ISNUMBER(FIND('1 - General description'!$H$60,F56)),ISNUMBER(FIND('1 - General description'!$H$61,F56)),ISNUMBER(FIND('1 - General description'!$H$62,F56)),ISNUMBER(FIND('1 - General description'!$H$63,F56)),ISNUMBER(FIND('1 - General description'!$H$64,F56))) -> TRUE
A57: 10 | B57: Security incidents / Incidents de sécurité | C57: 10.1 | D57: Reporting of incidents / Notification des incidents | E57: The service provider undertakes to notify the client, at the earliest opportunity and in any case no later than seventy-two (72) hours after detection, of any known security incidents, any detection of flaws or vulnerabilities, any detection of suspicious events which might affect the security of the client’s Information System or it's data, and of which the service provider might become aware. This also concerns the Information System of the service provider if it is in connection with the customer's one. Such incidents may include, but are not limited to, unavailability, attempted or successful intrusion, site defacement, data exposure or leakage, fraud or attempted fraud and identity theft. / Le prestataire s’engage à notifier au client dans les plus brefs délais, et dans tous les cas jamais après plus de 72 heures, toute faille de sécurité avérée, toute détection de vulnérabilité, toute détection d’évènement suspect pouvant porter atteinte à la sécurité du SI du client ou à ses données et dont ils auraient connaissance. Cela concerne le système d'information du prestataire lui-même, si celui-ci est en lien avec le client. Ces incidents peuvent être, sans que cette liste ne soit exhaustive, des indisponibilités, des tentatives d’intrusion ou des intrusions avérées, des défigurations de sites, des expositions ou des fuites de données, des fraudes ou des tentatives de fraude, des usurpations d’identité, etc. | F57: Z | G57: =IF(K57= TRUE,"Applicable","N.A") -> N.A | K57: =OR(ISNUMBER(FIND('1 - General description'!$H$51,F57)),ISNUMBER(FIND('1 - General description'!$H$52,F57)),ISNUMBER(FIND('1 - General description'!$H$53,F57)),ISNUMBER(FIND('1 - General description'!$H$54,F57)),ISNUMBER(FIND('1 - General description'!$H$55,F57)),ISNUMBER(FIND('1 - General description'!$H$56,F57)),ISNUMBER(FIND('1 - General description'!$H$57,F57)),ISNUMBER(FIND('1 - General description'!$H$58,F57)),ISNUMBER(FIND('1 - General description'!$H$59,F57)),ISNUMBER(FIND('1 - General description'!$H$60,F57)),ISNUMBER(FIND('1 - General description'!$H$61,F57)),ISNUMBER(FIND('1 - General description'!$H$62,F57)),ISNUMBER(FIND('1 - General description'!$H$63,F57)),ISNUMBER(FIND('1 - General description'!$H$64,F57))) -> FALSE
A58: 11 | B58: Security of developments / Sécurité des développements | C58: 11.1 | D58: State of the art / Etat de l'art | E58: The service provider shall ensure the security of developments in accordance with the current state of the art in the technologies it has chosen to implement. The development of web applications must be based on OWASP recommendations and take into account the OWASP top ten risks. / Le prestataire assure la sécurité des développements conformément à l’état de l’art actuel des technologies qu’il a choisi de mettre en œuvre. Le développement d’applications de type Web doit s’appuyer sur les recommandations de l’OWASP et prendre en compte les dix principaux risques identifiés par l'OWASP. | F58: E, F, G | G58: =IF(K58= TRUE,"Applicable","N.A") -> Applicable | K58: =OR(ISNUMBER(FIND('1 - General description'!$H$51,F58)),ISNUMBER(FIND('1 - General description'!$H$52,F58)),ISNUMBER(FIND('1 - General description'!$H$53,F58)),ISNUMBER(FIND('1 - General description'!$H$54,F58)),ISNUMBER(FIND('1 - General description'!$H$55,F58)),ISNUMBER(FIND('1 - General description'!$H$56,F58)),ISNUMBER(FIND('1 - General description'!$H$57,F58)),ISNUMBER(FIND('1 - General description'!$H$58,F58)),ISNUMBER(FIND('1 - General description'!$H$59,F58)),ISNUMBER(FIND('1 - General description'!$H$60,F58)),ISNUMBER(FIND('1 - General description'!$H$61,F58)),ISNUMBER(FIND('1 - General description'!$H$62,F58)),ISNUMBER(FIND('1 - General description'!$H$63,F58)),ISNUMBER(FIND('1 - General description'!$H$64,F58))) -> TRUE
A59: 11 | B59: Security of developments / Sécurité des développements | C59: 11.2 | D59: Patches / Correctifs | E59: Developments shall be regularly adapted to the recommendations and patches released by the publishers of the environments on which they rely. / Les développements sont régulièrement adaptés aux recommandations et correctifs des éditeurs des environnements sur lesquels ils s’appuient. | F59: E, F, G | G59: =IF(AND('1 - General description'!$G$51=FALSE, K59= TRUE),"Applicable","N.A") -> Applicable | K59: =OR(ISNUMBER(FIND('1 - General description'!$H$51,F59)),ISNUMBER(FIND('1 - General description'!$H$52,F59)),ISNUMBER(FIND('1 - General description'!$H$53,F59)),ISNUMBER(FIND('1 - General description'!$H$54,F59)),ISNUMBER(FIND('1 - General description'!$H$55,F59)),ISNUMBER(FIND('1 - General description'!$H$56,F59)),ISNUMBER(FIND('1 - General description'!$H$57,F59)),ISNUMBER(FIND('1 - General description'!$H$58,F59)),ISNUMBER(FIND('1 - General description'!$H$59,F59)),ISNUMBER(FIND('1 - General description'!$H$60,F59)),ISNUMBER(FIND('1 - General description'!$H$61,F59)),ISNUMBER(FIND('1 - General description'!$H$62,F59)),ISNUMBER(FIND('1 - General description'!$H$63,F59)),ISNUMBER(FIND('1 - General description'!$H$64,F59))) -> TRUE
A60: 11 | B60: Security of developments / Sécurité des développements | C60: 11.3 | D60: Best practices / Bonnes pratiques | E60: The application shall follow the principle of least privilege. Access to administrator functions must be secure. Strict control of user inputs and effective error management shall be implemented. The use of passwords inside the application’s code is prohibited. / L’application respecte le principe du moindre privilège. L’accès aux fonctions d’administration est sécurisé. Un contrôle rigoureux des entrées utilisateurs et une gestion efficace des erreurs sont assurés. Il est interdit d’utiliser des mots de passe dans le code de l’application. | F60: E, F, G | G60: =IF(K60= TRUE,"Applicable","N.A") -> Applicable | K60: =OR(ISNUMBER(FIND('1 - General description'!$H$51,F60)),ISNUMBER(FIND('1 - General description'!$H$52,F60)),ISNUMBER(FIND('1 - General description'!$H$53,F60)),ISNUMBER(FIND('1 - General description'!$H$54,F60)),ISNUMBER(FIND('1 - General description'!$H$55,F60)),ISNUMBER(FIND('1 - General description'!$H$56,F60)),ISNUMBER(FIND('1 - General description'!$H$57,F60)),ISNUMBER(FIND('1 - General description'!$H$58,F60)),ISNUMBER(FIND('1 - General description'!$H$59,F60)),ISNUMBER(FIND('1 - General description'!$H$60,F60)),ISNUMBER(FIND('1 - General description'!$H$61,F60)),ISNUMBER(FIND('1 - General description'!$H$62,F60)),ISNUMBER(FIND('1 - General description'!$H$63,F60)),ISNUMBER(FIND('1 - General description'!$H$64,F60))) -> TRUE
A61: 11 | B61: Security of developments / Sécurité des développements | C61: 11.4 | D61: Environments / Environnements | E61: The service provider shall use separate development, integration, staging and production environments. Development and integration environments must use anonymous test data. Non-production environments must never be exposed publicly on the Internet, in order to limit the risks of data leaks. / Le prestataire met en œuvre des environnements de développement, intégration, pré-production et production séparés. Les environnements de développement et d’intégration doivent utiliser des données fictives et/ou anonymes au sens de la réglementation applicable et des autorités de contrôle. Les environnements hors production ne doivent pas être exposés publiquement sur Internet, afin de limiter les risques de fuite de données. | F61: E, F, G | G61: =IF(AND('1 - General description'!$G$51=FALSE, K61= TRUE),"Applicable","N.A") -> Applicable | K61: =OR(ISNUMBER(FIND('1 - General description'!$H$51,F61)),ISNUMBER(FIND('1 - General description'!$H$52,F61)),ISNUMBER(FIND('1 - General description'!$H$53,F61)),ISNUMBER(FIND('1 - General description'!$H$54,F61)),ISNUMBER(FIND('1 - General description'!$H$55,F61)),ISNUMBER(FIND('1 - General description'!$H$56,F61)),ISNUMBER(FIND('1 - General description'!$H$57,F61)),ISNUMBER(FIND('1 - General description'!$H$58,F61)),ISNUMBER(FIND('1 - General description'!$H$59,F61)),ISNUMBER(FIND('1 - General description'!$H$60,F61)),ISNUMBER(FIND('1 - General description'!$H$61,F61)),ISNUMBER(FIND('1 - General description'!$H$62,F61)),ISNUMBER(FIND('1 - General description'!$H$63,F61)),ISNUMBER(FIND('1 - General description'!$H$64,F61))) -> TRUE
A62: 12 | B62: Audit | C62: 12.1 | D62: Internet exposure / Exposition internet | E62: In order to prevent data leakage, the client reserves the right to check that there are no vulnerabilities (actively and passively) in the systems used by the service provider for the storage of data which concerns the client and which are accessible through the Internet. Workload tests and penetration tests are not part of this requirement. / Afin d'éviter les fuites de données, le client se réserve le droit de vérifier qu'il n'y a pas de vulnérabilités (de manière active et passive) dans les systèmes utilisés par le prestataire pour le stockage des données qui le concernent et qui sont accessibles via Internet. Les tests de charge et les tests d'intrusion ne rentrent pas dans le cadre de cette exigence. | F62: A, B, C, D, E, F, G, H, I, J, K, L, M | G62: =IF(AND('1 - General description'!$G$51=FALSE, K62= TRUE),"Applicable","N.A") -> Applicable | K62: =OR(ISNUMBER(FIND('1 - General description'!$H$51,F62)),ISNUMBER(FIND('1 - General description'!$H$52,F62)),ISNUMBER(FIND('1 - General description'!$H$53,F62)),ISNUMBER(FIND('1 - General description'!$H$54,F62)),ISNUMBER(FIND('1 - General description'!$H$55,F62)),ISNUMBER(FIND('1 - General description'!$H$56,F62)),ISNUMBER(FIND('1 - General description'!$H$57,F62)),ISNUMBER(FIND('1 - General description'!$H$58,F62)),ISNUMBER(FIND('1 - General description'!$H$59,F62)),ISNUMBER(FIND('1 - General description'!$H$60,F62)),ISNUMBER(FIND('1 - General description'!$H$61,F62)),ISNUMBER(FIND('1 - General description'!$H$62,F62)),ISNUMBER(FIND('1 - General description'!$H$63,F62)),ISNUMBER(FIND('1 - General description'!$H$64,F62))) -> TRUE

Sheet 4 - 3rd Party Assessment 
B2: ASSESSMENT / EVALUATION | I2: Applicability / Applicabilité
B3: Chapter | C3: General questions | D3: Questions générales | E3: Client comments / Commentaires du Client | G3: Reference document / Document de référence | H3: Assessment / Evaluation (by SEPHORA) | I3: Applicable
B4: 1 | C4: INFORMATION SECURITY POLICY / POLITIQUE DE SECURITE DE L'INFORMATION
B5: POL-01 | C5: Do you have a general Information Security Policy ? Is it available for reading (URL, attached file) ? Please could you provide the PSSI to LVMH team security ? | D5: Possédez-vous une Politique générale Sécurité (PSSI)? Est-elle disponible pour consultation (URL, fichier attaché)? Pourriez-vous transférer votre PSSI lors de l'envoi de votre réponse à l'équipe de sécurité de LVMH ?
B6: POL-01-1 | C6: Have you set up an IT/cyber risk management process (formalised, equipped, monitored)? Do you have action plans to monitor these risks? | D6: Avez-vous mis en place un processus (formalisé, outillé, contrôlé) de gestion des risques IT/cyber? Est-ce que vous avez des plans de suivi d'actions de ces risques?
B7: POL-01-2 | C7: Have you implemented a "security by design" management process (formalised, equipped, monitored) in all your internal projects ? Is this process put in place for each new project? Please could you list the steps of the process in place? | D7: Avez-vous mis en place un processus (formalisé, outillé, contrôlé) de gestion "security by design" pour l'ensemble de vos projets internes? Est-ce que ce processus est mis en place pour chaque nouveau projet? Pouvez-vous lister les étapes du processus en place?
B8: 2 | C8: INFORMATION SECURITY ORGANIZATION / ORGANISATION DE LA SECURITE DE L'INFORMATION
B9: ORG-01 | C9: Cie Nationality / Head Office Name and Nationality | D9: Nationalité / Nom de la société et localisation du Siège de la Société
B10: ORG-02 | C10: Member of a Group of companies / Controlling shareholder / international coverage | D10: Appartenance à un groupe d'entreprise / Actionnaire majoritaire / Présence internationale
B11: ORG-03 | C11: Company's headcount | D11: Effectifs de la société
B12: ORG-04 | C12: IT headcount | D12: Effectifs des équipes IT
B13: ORG-05 | C13: Cybersecurity headcount | D13: Effectifs des équipes cyber sécurité
B14: ORG-06 | C14: Person in charge of security of the solution / the services (email contact) | D14: Responsable de la sécurité pour la sécurité de l'offre (préciser l'adresse de contact)
B15: ORG-07 | C15: Chief Information Security Officer of the company | D15: Responsable cybersécurité pour la sécurité globale de l'entreprise (RSSI/CISO)
B16: ORG-08 | C16: Company security certificates - detailed scope and certifying body Can you please provide certificates to LVMH team security? | D16: Certifications sécurité de la société - Préciser le périmètre et organisme certificateur Pouvez-vous nous transmettre le(s) certificat(s) lors de l'envoi de votre réponse à l'équipe de sécurité de LVMH?
B17: ORG-09 | C17: How often do you assess the maturity of your cybersecurity? On the basis of which framework (e.g. CIS20, internal framework) ? Is this assessment done by a third party? Do you monitor cyber threats? (describe briefly) | D17: A quelle fréquence, procédez-vous à une évaluation de la maturité de votre cybersécurité ? Sur la base de quel framework (ex : CIS20, framework interne) ? Cette évaluation est-elle accompagnée par un tiers ? Est-ce que vous réalisez des veilles sur les menaces cyber? Quelle(s) méthode(s) utilisez-vous?
B18: ORG-10 | C18: Is information security integrated into the project management method(s)? Please specify. | D18: La sécurité de l'information est-elle intégréé dans la ou les méthodes de gestion de projet ? Précisez.
B19: 3 | C19: HUMAN RESOURCES SECURITY / SECURITE LIEE AUX RESSOURES HUMAINES
B20: HUM-01 | C20: Are there any clauses in each employment contract regarding the employee's responsibilities (with respect to ISS)? If so, which aspects do they cover? | D20: Des clauses relatives aux responsabilités (en matière de SSI) du collaborateur figurent-elles dans chaque le contrat de travail ? Si oui, sur quels aspects portent-elles ?
B21: HUM-02 | C21: How do you ensure that your employees are aware of and trained in security? How often? Have you identified which of your employees are most at risk? | D21: Comment assurez-vous la sensibilisation et formation à la sécurité de vos collaborateurs? A quelle fréquence le faites-vous? Avez-vous identifié parmi vos collaborateurs les populations les plus à risque ?
B22: HUM-03 | C22: Are your employees subject to a user security charter? | D22: Vos collaborateurs sont ils soumis à une charte sécurité utilisateurs ?
B23: HUM-04 | C23: Are your administrators with privileged accounts subject to a specific security policy? | D23: Vos administrateurs détenteurs de comptes à privilèges sont ils soumis à une charte sécurité spécifique ?
B24: 4 | C24: ASSET MANAGEMENT / GESTION DES ACTIFS
B25: ACT-01 | C25: Is an inventory of the assets associated with the information and the means of information processing established and maintained? | D25: Un inventaire des actifs associés à l'information et aux moyens de traitement de l'information est-il dressé et tenu à jour ?
B26: ACT-02 | C26: How are the aspects related to reversibility addressed by your company? | D26: Comment les aspects liés à la réversibilité sont-ils adressés par votre société ?
B27: ACT-03 | C27: In particular, do you provide the necessary assistance during the migration period to facilitate the transfer of hardware and software resources, as well as the resumption of their exploitation by SEPHORA or another service provider? | D27: En particulier, apportez-vous l'assistance nécessaire durant la période de migration pour faciliter le transfert des moyens matériels et logiciels, ainsi que la reprise de leur exploitation par SEPHORA ou un autre prestataire de service ?
B28: ACT-04 | C28: Is the information classified in terms of value, legal requirements and sensitivity? In particular, is a classification of the documents made ? Describe this classification. | D28: Une classification des informations en termes de valeur, d'exigences légales et de sensibilité est-elle effectuée ? En particulier, une classification des documents est-elle effectuée ? Décrire cette classification.
B29: 5 | C29: ACCESS CONTROL / CONTRÔLE D'ACCES
B30: IAM-01 | C30: Is an access control policy formalized? Briefly describe it. | D30: Une politique de contrôle des accès est-elle formalisée ? La décrire succintement.
B31: IAM-02 | C31: Do you have an identity and access management process (formalised, equipped, monitored) for all your employees? Please could you detail your process in place ? How all identities are managed? | D31: Disposez-vous, au sein de la société, d'un processus (formalisé, outillé, contrôlé) de gestion des identités et des accès pour l'ensemble de vos collaborateurs ? Si oui, pouvez-vous nous lister les points clés de cette politique de gestion des accès? Par quels moyens sont gérés l'ensemble des identités?
B32: IAM-03 | C32: How are authentications managed (presence of SSO, MFA, federation) for the company's employees and subcontractors on the main information systems, especially critical systems? | D32: Comment sont gérés les authentifications (présence de SSO, MFA, fédération) pour les employés et sous-traitants de la société sur les principaux systèmes d'information, et notamment les systèmes critiques ?
B33: IAM-04 | C33: How do you manage the roles of people with privileged accounts: what access control? Do you use MFA for privileges accounts? What segregation of duties and what least privilege principle? Do you use a PAM (Privilege Access Management)? | D33: Comment gérez-vous les rôles des personnes ayant des comptes à privilèges : quel contrôle d'accès ? Utilisez-vous du MFA pour les comptes à privilèges? Quelle ségrégation des tâches et quel principe du moindre privilège? Utilisez-vous un PAM (Privilege Access Management)?
B34: IAM-05 | C34: Are user access rights reviewed regularly? If so, according to what process? | D34: Les droits d'accès utilisateur sont-ils revus régulièrement ? Si oui, selon quel processus ?
B35: 6 | C35: CRYPTOGRAPHY / CRYPTOGRAPHIE
B36: CRY-01 | C36: Is there a policy for the use of cryptographic mechanisms? If yes, on which reference(s) is it based? (e.g.: ANSSI guidelines, NIST, OWASP recommendations, etc.) | D36: Existe-il une politique d'utilisation des mécanismes cryptographiques ? Si oui, sur quel(s) référentiel(s) est-elle basée ? (ex: recommandations de l'ANSSI, du NIST, de l'OWASP, etc.)
B37: CRY-02 | C37: How is customer data protected in storage? Specify how data confidentiality and integrity are ensured. | D37: Comment les données client sont-elles protégées en stockage ? Précisez comment la confidentialité et l'intégrité des données sont assurées.
B38: 7 | C38: PHYSICAL AND ENVIRONMENTAL SECURITY / SECURITE PHYSIQUE ET ENVIRONNEMENTALE
B39: PHY-01 | C39: What is the location of the premises related to the service? Are your offices located in a co-working space? | D39: Quelle est la localisation des locaux liés à la prestation ? Vos locaux sont-ils situés dans un espace de co-working?
B40: PHY-02 | C40: Are they located in areas not subject to natural disasters?_x000D_ (e.g. floods, storms, etc.) | D40: Sont-ils situés dans des zones non sujettes aux catastrophes naturelles ? (ex: crues, tempêtes, etc.)
B41: PHY-03 | C41: Present the technical security devices aimed at ensuring physical protection of the premises concerned (e.g.: access control by badge, surveillance cameras, armored doors, etc.) | D41: Présenter les dispositifs de sécurité techniques visant à assurer une protection physique des locaux concernés (ex: contrôle d'accès par badge, caméras de surveillance, portes blindées, etc.)
B42: PHY-04 | C42: Present the human security devices aimed at ensuring physical protection of the premises concerned._x000D_ (e.g.: security guards on the premises, guarding, employee awareness, etc.) | D42: Présenter les dispositifs de sécurité humains visant à assurer une protection physique des locaux concernés. (ex: agents de sécurité dans les locaux, gardiennage, sensibilisation des collaborateurs, etc.)
B43: PHY-05 | C43: Present the physical and logical security measures in place for working in any secured areas. | D43: Présenter les mesures de sécurité physiques et logiques mises en place pour le travail dans les éventuelles zones sécurisées.
B44: DATACENTERS
B45: PHY-06-1 | C45: Is the Datacenters service provided by the Company? | D45: Est-ce que le service Datacenters est fourni par la Société ?
B46: PHY-06-2 | C46: If not, please specify the name of the owner of the datacenter(s) | D46: Sinon, préciser le nom du propriétaire du ou des datacenters
B47: PHY-06-3 | C47: Number and location of data centers | D47: Nombre et localisation des datacenters
B48: PHY-06-4 | C48: Certifications of the data centers | D48: Certifications des datacenters | G48: ex: Certification ISO27001
B49: PHY-06-5 | C49: Physical and environmental protection of data centers (physical access control, energy, air conditioning, fire, flood, lightning, earthquakes) | D49: Protection physique et environnementale des datacenters (contôle des accès physiques, énergie, climatisation, incendie, inondation, foudre, séismes)
B50: 8 | C50: OPERATIONAL SECURITY / SECURITE LIEE A L'EXPLOITATION
B51: EXP-01 | C51: What security measures have you put in place for your workstations and mobile devices? Which of the following features have you implemented: hardening, EPP, EDR, MDM, patch management, anti-malware VPN? Do you have BYOD in place? | D51: Quels dispositifs de sécurisation avez-vous mis en place pour vos postes de travail et équipements nomades? Parmi les dispositifs suivants, indiquez lesquels vous avez implémenté : durcissement, EPP, EDR, MDM, patch management et anti-malware VPN ? Avez-vous mis en place du BYOD?
B52: EXP-02 | C52: What security measures have you put in place for your servers? Which of the following features have you implemented: hardening, EPP, EDR, patch management, internet access protection, WAF, reverse proxy and anti DDOS tools? | D52: Quel dispositif de sécurisation avec-vous mis en place pour vos serveurs ? Parmi les dispositifs suivants, indiquez lesquels vous avez implémenté : durcissement, EPP, EDR, patch management, protection de l'accès à Internet, WAF, Reverse proxy et des outils anti DDOS ?
B53: EXP-03 | C53: What general network security measures have you put in place? Which of the following features have you implemented: IPS/IDS, perimeter FW and segregation? | D53: Quels moyens de sécurisation générale de vos réseaux avez-vous mis en place? Parmi les dispositifs suivants, indiquez lesquels vous avez implémenté : IPS/IDS, FW périmétrique, ségmentation ?
B54: EXP-04 | C54: How is the traceability of events (including security events) ensured?_x000D_ (e.g. technical logs, application logs, monitoring logs, etc.) | D54: Comment la traçabilité des évènements (dont évènements de sécurité) est-elle assurée ? (ex: logs techniques, logs applicatifs, logs de monitoring, etc.)
B55: 9 | C55: SECURITY OF COMMUNICATIONS / SECURITE DES COMMUNICATIONS
B56: COM-01 | C56: How is customer data protected in transit? Specify how data confidentiality and integrity are ensured. | D56: Comment les données client sont-elles protégées en transport ? Préciser comment la confidentialité et l'intégrité des données sont assurées.
B57: COM-02 | C57: Are groups of information services, users and information systems partitioned on the networks? | D57: Les groupes de services d'information, d'utilisateurs et de systèmes d'information sont-ils cloisonnés sur les réseaux ?
B58: COM-03 | C58: What security measures are in place to protect information passing through email? | D58: Quels sont les mesures de sécurité mises en place pour protéger l'information transitant par la messagerie électronique ?
B59: 10 | C59: ACQUISITION, DEVELOPMENT AND MAINTENANCE OF INFORMATION SYSTEMS / ACQUISITION, DEVELOPPEMENT ET MAINTENANCE DES SI
B60: DEV-01 | C60: What security standard(s) and/or recommendations does your company rely on when developing its applications?_x000D_ (e.g. Top 10 OWASP, CERT Secure Coding Standards, Top 25 SANS, etc.) | D60: Sur quel(s) référentiel(s) de sécurité et/ou quelles recommandations votre société se base-t-elle pour le développement de ses applicatifs ? (ex: Top 10 OWASP, CERT Secure Coding Standards, Top 25 SANS, etc.)
B61: DEV-02 | C61: Are developers trained in secure development best practices? Specify the frequency and the operating mode_x000D_ (e.g. face-to-face training, specific mandatory e-learning modules, etc.) | D61: Les développeurs sont-ils formés aux bonnes pratiques de développement sécurisé ? Précisez la fréquence et le mode opératoire (ex: formations en présentiel, modules e-learnings spécifiques obligatoires, etc.)
B62: DEV-03 | C62: How do you ensure the security and integrity of your software development? How do you protect against the introduction of malicious software into the development chain? | D62: Comment assurez-vous la sécurité et la protection de l'intégrité de vos développements logiciels ? Comment vous prémunissez-vous contre l'introduction de logiciels malveillants dans la chaîne de développement ?
B63: 11 | C63: RELATIONSHIP WITH SUPPLIERS / RELATION AVEC LES FOURNISSEURS
B64: FOU-01 | C64: How do you manage your suppliers? Have you identified all the third parties involved in the implementation of your offer (hosts, developers, integrators, etc.)? | D64: Comment gérez-vous vos fournisseurs ? Avez-vous recensé l'ensemble des tiers participant à la mise en œuvre de votre offre (hébergeurs, développeurs, intégrateurs, etc.) ?
B65: FOU-02 | C65: Which third parties does your company use for this service? Specify their respective roles within the framework of the service. | D65: Quels sont les éventuels tiers auquels votre société dans le cadre de cette prestation ? Précisez leurs rôles respectifs.
C66: How do you manage your suppliers? Do you do security assessments of your suppliers? How often? How do you manage the risk assessment of your suppliers? What method do you use? | D66: Evaluez-vous la sécurité de vos fournisseurs? A quelle fréquence le faites vous ? Comment gérez-vous l'évaluation des risques liés à vos fournisseurs? Quelle(s) méthode(s) utilisez-vous?
B67: FOU-03 | C67: Do you contractualize the security requirements imposed by your customers to the third parties you use? _x000D_ _x000D_ (SEPHORA imposes on its service providers to transfer to the third parties concerned security requirements equivalent to those that these service providers commit to implement within the framework of the contract that links them to SEPHORA). | D67: Contractualisez-vous les exigences de sécurité imposées par vos clients auprès des tiers auquels vous avez recours ? (SEPHORA impose en effet à ses prestataires de reporter vers les tiers concernés des exigences de sécurité équivalentes à celles que ces prestataires s'engagent à mettre en oeuvre dans le cadre du contrat qui les lies à SEPHORA) | G67: ex: modèle de Plan d'Assurance Sécurité
B68: FOU-04 | C68: Do you control the application of security measures by these third parties? If yes, how?_x000D_ (e.g.: surveillance, security audits, security visits, etc.) | D68: Contrôlez-vous l'application des mesures de sécurité par ces tiers ? Si oui, comment ? (ex: surveillance, audits de sécurité, visites de sécurité, etc.) | G68: ex: Questionnaire/checklist sécurité
B69: 12 | C69: SECURITY INCIDENT MANAGEMENT / GESTION DES INCIDENTS DE SECURITE
B70: INC-01 | C70: Do you have a security incident management process (formalised, equipped, monitored)? Could you briefly describe your process? | D70: Disposez-vous d'un processus (formalisé, outillé, contrôlé) de gestion des incidents de sécurité? Pouvez-vous décrire brièvement le processus?
B71: INC-02 | C71: Do you have a SOC/CERT service? Is it in-house, outsourced, hybrid? Does it operate 24/7? Does it cover monitoring of the solution/services contracted? | D71: Disposez-vous d'un service de SOC/CERT ? Est-il interne, externalisé, hybride ? Fonctionne-t-il en 24/7 ? Couvre-t-il la surveillance de la solution / des services objet du contrat ?
B72: 13 | C72: ISS ASPECTS IN BUSINESS CONTINUITY MANAGEMENT / ASPECTS SSI DANS LA GESTION DE LA CONTINUITE D'ACTIVITE
B73: PCA-01 | C73: Is a global business continuity management process formalized and implemented? | D73: Un processus global de gestion de continuité de l'activité est-il formalisé et mis en place ?
B74: PCA-02 | C74: Are there specific variations of this same process for certain entities in your company? | D74: Existe-t-il des déclinaisons de ce même processus spécifiques à certaines entités de votre société ?
B75: PCA-03 | C75: What are the redundancy means implemented to guarantee the maximum availability of IT services? | D75: Quels sont les moyens de redondance mis en œuvre pour garantir le maximum de disponibilité des services IT ?
B76: PCA-04 | C76: Are redundant information systems tested to ensure that the switchover from one component to another works as planned? Specify. | D76: Les systèmes d'information redondants sont-ils testés afin de s'assurer que le basculement d'un composant à un autre fonctionne comme prévu ? Précisez.
B77: 14 | C77: COMPLIANCE / CONFORMITE
B78: CON-01 | C78: What are your company's security certifications, if any? Specify the scope and year obtained or recertified._x000D_ (ex: ISO/IEC 27001:2013, PCI DSS v3.2, PASSI, etc.) | D78: Quelles sont les éventuelles certifications sécurité de votre société ? Précisez le périmètre et l'année d'obtention ou de recertification. (ex: ISO/IEC 27001:2013, PCI DSS v3.2, PASSI, etc.)
B79: CON-02 | C79: Can you specify the auditability clauses of your services and products?_x000D_ SEPHORA is indeed likely to trigger an audit (by itself or by an approved third party) according to the clauses provided in the contract that binds it to its service providers. | D79: Pouvez-vous préciser les clauses d'auditabilité de vos services et produits ? SEPHORA est en effet susceptible de déclencher un audit (par ses soins ou par un tiers agrée) selon les clauses prévues dans le contrat qui le lie à ses prestataires.
B80: CON-03 | C80: Do you carry out security audits (internal or external)? If so, on what perimeter and how often? | D80: Procédez-vous à des audits de sécurité (internes ou externes) ? Si oui, sur quel périmètre et selon quelle fréquence ?
B81: CON-04 | C81: What are the main technical and organizational measures put in place (or identified) to ensure compliance with the European GDPR regulation?_x000D_ (e.g. appointment of a DPO, inventory of personal data processing, anonymization/pseudonynmization, etc.). | D81: Quelles sont les principales dispositions techniques et organisationnelles mises en place (ou identifiées) pour assurer une conformité vis-à-vis du règlement européen GDPR ? (ex: nomination d'un DPO, recensement des traitements de données à caractère personnel, anonymisation/pseudonynmisation, etc.)
B83: QUESTIONS IN CASE OF / QUESTIONS EN CAS DE
B84: Chapter | C84: General questions | D84: Questions générales | E84: Client comments / Commentaires du Client | G84: Reference document / Document de référence | H84: Assessment / Evaluation (by SEPHORA) | I84: Applicability / Applicabilité
B85: CB | C85: CREDIT CARD DATA ARE PROCESSED / TRAITEMENT DE DONNEES DE CARTES BANCAIRES | I85: =IF('2 - Qualification'!E27="yes","Applicable","N.A") -> N.A
B86: CB-01 | C86: How is this data captured (POS, website, telephone, other) | D86: Par quel moyen cette donnée est-elle captée (terminal de paiement, site web, téléphone, autre)
B87: CB-02 | C87: If it is capturde by devices, implementation of P2PE or E2EE ? | D87: Si captée par les terminaux, mise en œuvre de P2PE ou E2EE ?
B88: CB-03 | C88: Is credit card data handled (regardless of storage) ? | D88: La donnée CB est-elle manipulée (indépendament de son stockage) ?
B89: CB-04 | C89: Is credit card data stored ? | D89: La donnée CB est-elle stockée ?
B90: CB-05 | C90: PCI-DSS compliance (last RoC to be provided) | D90: Conformité PCI-DSS (Merci de fournir votre dernier RoC )
B91: CB-06 | C91: If compliant, compliance perimeter | D91: Si oui, périmètre de conformité
B92: CB-07 | C92: If compliant, compliance perimeter | D92: Comment s'assure-t-on que le périmètre de conformité est pertinent et le reste dans le temps ?
B93: CB-08 | C93: Do ASV scans exist? | D93: Existence de scans ASV ?
B94: CB-09 | C94: Control mode : audit or self assessment | D94: Mode de vérification : audit / self-assessment
B95: CB-10 | C95: If self-assessment, category of self-assessment | D95: Si self-assessment, type de self-assessment
B96: CB-11 | C96: Compliance of sub-contractors | D96: Conformité des sous-traitants
B97: CB-12 | C97: How do you control that sub-contractors are compliant ? | D97: Quel mode de vérification de la conformité des sous-traitants ?
B98: CB-13 | C98: Technical and organizational security controls to protect card data | D98: Mesures techniques et organisationnelles de sécurité pour protéger les données carte
B100: Chapter | C100: General questions | D100: Questions générales | E100: Client comments / Commentaires du Client | G100: Reference document / Document de référence | H100: Assessment / Evaluation (by SEPHORA) | I100: Applicability / Applicabilité
B101: SA | C101: SAAS - IAAS - PAAS MODE APPLICATIONS / PRESTATIONS D'APPLICATIONS SAAS - IAAS - PAAS | I101: =IF(OR('1 - General description'!$C$11="Cloud / SaaS",'1 - General description'!E42="Yes"),"Applicable","N.A") -> Applicable
B102: Application layer / Niveau applicatif
B103: SA-01-1 | C103: Main functions | D103: Principales fonctions réalisées
...

Sheet 5 - Risk Assessment
B1: TOP RISKS : CYBER AND PRIVACY IMPACT (IF PIA)
H2: To be filled if PIA required
B3: Risk id | C3: Risk description | D3: Due to…. Threat scenarios | E3: Type of risk | F3: Impact description of cyber risk (company's perspective if applicable) | G3: Impact level (1: none or low, 2:medium, 3:high, 4:very high) | H3: Impact description of privacy risk (subjects' privacy perspective if applicable) | I3: Impact level (1: none or low, 2:medium, 3:high, 4:very high) | J3: Likelihood (1: very low, 2:low, 3:medium, 4:high) | K3: Global risk value (1 to 16) | L3: Global risk level (severity: LOW, MEDIUM or HIGH) | M3: Residual risk accepted | N3: Comments
A4: TOP risks | B4: R1 | C4: Data disclosure | D4: -Lack of Protection tools and monitoring of key systems - Malware infection and propagation - Misuse of priviledge account - Identity theft of priviledge account | E4: Cyber & Privacy | F4: '-Penalties by competent Authorities due to non-Compliance for lack of protection of personal data -Claims by subjets -Reputational damage with indirect loss of business | G4: 4 | J4: 3 | K4: =MAX(G4,I4)*J4 -> 12 | L4: =IF(K4<4,"LOW",IF(K4>9,"HIGH","MEDIUM")) -> HIGH
B5: R2 | C5: Unauthorized access to data and company or subjects lose control over their data | D5: -Lack of Protection tools and monitoring of key systems - Malware infection and propagation - Misuse of priviledge account - Identity theft of priviledge account | E5: Cyber & Privacy | F5: '-Penalties by competent Authorities due to non-Compliance for lack of protection of personal data -Reputational damage with indirect loss of business | G5: 4 | J5: 4 | K5: =MAX(G5,I5)*J5 -> 16 | L5: =IF(K5<4,"LOW",IF(K5>9,"HIGH","MEDIUM")) -> HIGH
B6: R3 | C6: Unautorized/unwanted changes that lead to malfunction and errors (data/systems have been modified voluntarily or not) | D6: - Lack of consistent users provisioning and deprovisioning process to enforce segregation of duties - Lack of Protection tools and monitoring of key systems - Malware infection and propagation - Misuse of priviledge account - Identity theft of priviledge account | E6: Cyber | F6: Fraud in case of modification of Customer delivery address Disruption, productivity loss | G6: 4 | J6: 3 | K6: =MAX(G6,I6)*J6 -> 12 | L6: =IF(K6<4,"LOW",IF(K6>9,"HIGH","MEDIUM")) -> HIGH
B7: R4 | C7: Business Disruption/ Unavailability of application/Service | D7: -Lack of redundancy -Lack of Protection tools and monitoring of key systems - Malware infection and propagation - Misuse of priviledge account - Identity theft of priviledge account | E7: Cyber | F7: -Customers are not able to log-in in the Ecommerce app -Lost of revenu, no sales -Reputational damage with direct loss of business - Disruption, productivity loss | G7: 3 | J7: 2 | K7: =MAX(G7,I7)*J7 -> 6 | L7: =IF(K7<4,"LOW",IF(K7>9,"HIGH","MEDIUM")) -> MEDIUM
B8: R5 | C8: Data lost | D8: + Unable to restore data or system because backup wasn’t correctly executed and checked, and restoration process was never tested -Lack of Protection tools and monitoring of key systems - Unsecure data transfer / storage used by 3rd party - Malware infection and propagation - Misuse of priviledge account - Identity theft of priviledge account | E8: Cyber | F8: '-Penalties by competent Authorities due to non-Compliance for lack of protection of personal data -Claims by subjets -Reputational damage with indirect loss of business - Disruption, productivity loss | G8: 3 | J8: 3 | K8: =MAX(G8,I8)*J8 -> 9 | L8: =IF(K8<4,"LOW",IF(K8>9,"HIGH","MEDIUM")) -> MEDIUM
B9: R6 | C9: Theft of customer payment information | D9: Unsecure process for sending SMS and emailing to end customer See details of pentest report | E9: Cyber & Privacy | F9: Fraud in case of fake purchases on behalf of megitimate customer -Reputational damage with indirect loss of business - Rrisk of Non-Compliance for lack of protection of personal data | G9: 4 | J9: 1 | K9: =MAX(G9,I9)*J9 -> 4 | L9: =IF(K9<4,"LOW",IF(K9>9,"HIGH","MEDIUM")) -> MEDIUM | N9: Controls to protect Payment customer information reviewed by externatl auditor CNPP in the framework of PCI-DSS Certitication
B10: R7 | G10: 4 | J10: 2 | K10: =MAX(G10,I10)*J10 -> 8 | L10: =IF(K10<4,"LOW",IF(K10>9,"HIGH","MEDIUM")) -> MEDIUM
K11: =MAX(G11,I11)*J11 -> 0
B15: SECURITY CONTOLS - RISK TREATMENT
B16: Domain | C16: Control ID | D16: Control description | E16: Selected measure | F16: Description of the measure | G16: Risks list (Ri, Rj,...) | H16: Implementation date | I16: Implementation status | J16: Comment
B17: Security Policy | C17: SP01 | D17: Applicability of SEPHORA - Ecommerce Information Security Policy | E17: Mandatory - P1
C18: SP02 | D18: Applicability of SEPHORA - LVMH - Network security policy
C19: SP03 | D19: Applicability of SEPHORA - Sephora - Mobile Devices Security Policy
C20: SP04 | D20: Applicability of SEPHORA - Sephora - Point of Sale Security Policy
C21: SP05 | D21: Applicability of SEPHORA - Sephora - web site information security policy
C22: SP06 | D22: Applicability of SEPHORA - Sephora- Privileged accounts Security policy
C23: SP07 | D23: Applicability of SEPHORA - Sephora - Log Management Security Policy
C24: SP08 | D24: Applicability of Sephora developement security policy
B25: Third party | C25: M01 | D25: Contract with provider includes security clauses, SLA, and 3rd party Security Policy…
C26: M02 | D26: Third parties solutions used by the partner (SMS/emailing) include security clauses and 3rd party secureity policy
B27: Hosting | C27: M03 | D27: Physical & environmental protection of datacenters (physical access controls, power supply, climate control, fire, flooding, earthquake…)
C28: M04 | D28: Datacenter's certifications
B29: Architecture | C29: M05 | D29: Virtualized environment
C30: M06 | D30: Dedicated environment (no mutualization between customers)
C31: M07 | D31: 3 tier architecture
C32: M08 | D32: Network separation, firewall, flows and filtering matrix
C33: M09 | D33: Flows encryption, secured protocols…
C34: M10 | D34: Secured interfaced between applications (authentication, encryption…)
C35: M11 | D35: Separated environments : development, staging and production
C36: M12 | D36: Web application filtering (reverse-proxy, WAF…)
C37: M13 | D37: Protection against Denial-of-Service
C38: M14 | D38: Intrusion detection system
C39: M15 | D39: Malware protection
C40: M16 | D40: Hardening of systems, middlewares and applications
C41: M17 | D41: Patch management (servers, equipment, applications, databases, middlewares)
B42: Endpoint client | C42: M18 | D42: Laptop encryption
C43: M19 | D43: Mobile device management
C44: M20 | D44: Antimalware + EDR
C45: M21 | D45: Hardening systems of workstations and laptops
C46: M22 | D46: Patch management (workstations, laptops)
C47: M23 | D47: Network access control
C48: M24 | D48: Restrict Local access rights to end users
C49: M25 | D49: No BYOD allowed, only corporate clients
B50: Continuity | C50: M26 | D50: Data backup solution and backup strategy
C51: M27 | D51: Off-site data backup storage
C52: M28 | D52: High-availabilty solutions
C53: M29 | D53: DRP, DRP tested regularly
C54: M30 | D54: Supervision (parameters, configuration reviews, real time monitoring…), availability SLA follow-up
B55: IAM | C55: M31 | D55: Users accounts provisioning /de-provisioning
C56: M32 | D56: Formal commitment of the users
C57: M33 | D57: Identity Federation : authentication delegated to Active Directory
C58: M34 | D58: SSO
C59: M35 | D59: Local account and password policy (length, complexity, lifetime…)
C60: M36 | D60: Multi-factor authentication
C61: M37 | D61: Separation of Duties (SoD) & Role management . Mainly Between standard and Admin role
C62: M38 | D62: Periodical accounts reviews
C63: M39 | D63: Bastion for connection by 3rd parties
B64: Developpement | C64: M40 | D64: Security development charter
C65: M41 | D65: Security development training
C66: M42 | D66: Code review execution and remediation
B67: Logs | C67: M43 | D67: Logs exist, direct access by administrator and export on demand.
C68: M44 | D68: Logs collected and monitored by the Cyber SOC
B69: Audit | C69: M45 | D69: Configuration audit
C70: M46 | D70: White/Black/Grey box pentest
C71: M47 | D71: Audit results provided by supplier
C72: M48 | D72: Recurrent vulnerability scans
B73: Data | C73: M49 | D73: Data integrity checks (reviews, automatic checks…)
C74: M50 | D74: Data segregation (dedicated database, for example)
C75: M51 | D75: Anonymization for all data
C76: M52 | D76: Anonymized data on development and staging environment
C77: M53 | D77: Pseudonymization / Tokenisation
C78: M54 | D78: Watermarks for data and/or documents
C79: M55 | D79: Data Leak Prevention solution
C80: M56 | D80: Shadow IT : detection / prevention
C81: M56 | D81: URL filtering - Servers
C82: M57 | D82: URL filtering - Workstation
C83: M58 | D83: Hardware encryption
C84: M59 | D84: Database and/or file encryption
C85: M60 | D85: Data removal when hardware is deprovisioned
... C87: M62 | D87: Physical protection on printed data/documents and other papers containing data
B88: Privacy | C88: M63 | D88: Solution for extracting data for access or portability
C89: M64 | D89: Solution for retention period (automatic purge)
C90: M65 | D90: Solution for selective removal of data / Anonimization
C91: M66 | D91: Personal data stored in EU or in a equivalent location
C92: M67 | D92: Administrators/operators/helpdesk located in EU or in a equivalent location
C93: M68 | D93: Awareness / training sessions for IT people
C94: M69 | D94: Awareness / training sessions for IT people
C95: M70 | D95: Publication of procedures for personal data handling
B96: Incident | C96: M71 | D96: Incident management process including crisis management process and data breach notification
B97: Other (custom measures) | C97: M72 | D97: Cookies management according to the law

Sheet Paramètres
A1: Score
A2: 1
A3: 2
A4: 3
A5: 4
A8: Partie concernée | C8: Parties
A9: le client | C9: client
A10: le prestataire | C10: service provider
A11: les parties | C11: both parties
A13: Party
A14: customer
A15: provider
A16: parties
A18: Conformité
A19: Full
A20: Partial
A21: Not compliant
A23: Compliance
A24: Full
A25: Partial
A26: Not compliant
A28: Critères / Criteria
A29: 1
A30: 2
A31: 3
A32: 4
A34: Applicaibilité
A35: Oui
A36: n.a.
A38: Applicaibility
A39: Yes
A40: n.a.
A42: Applicable
A43: Oui / Yes
A44: n.a.
